Workbook

Sheet FD
A1: Country | C1: Country code | D1: Data type | E1: 2000 | F1: 2001 | G1: 2002 | H1: 2003 | I1: 2004 | J1: 2005 | K1: 2006 | L1: 2007 | M1: 2008 | N1: 2009 | O1: 2010 | P1: 2011 | Q1: 2012 | R1: 2013 | S1: 2014 | T1: 2015 | U1: 2016 | V1: 2017 | W1: 2018 | X1: 2019 | Y1: 2020 | Z1: 2021 | AC1: AVERAGE
A2: Angola | C2: AGO | D2: Financial Development Index | E2: 0.09 | F2: 0.09 | G2: 0.1 | H2: 0.1 | I2: 0.11 | J2: 0.11 | K2: 0.12 | L2: 0.13 | M2: 0.14 | N2: 0.16 | O2: 0.15 | P2: 0.14 | Q2: 0.13 | R2: 0.14 | S2: 0.13 | T2: 0.15 | U2: 0.15 | V2: 0.15 | W2: 0.14 | X2: 0.1 | Y2: 0.13 | Z2: 0.14 | AC2: =AVERAGE(E2:Z2) -> 0.12727273
A3: Bangladesh | C3: BGD | D3: Financial Development Index | E3: 0.22 | F3: 0.19 | G3: 0.2 | H3: 0.21 | I3: 0.19 | J3: 0.16 | K3: 0.14 | L3: 0.15 | M3: 0.19 | N3: 0.2 | O3: 0.23 | P3: 0.21 | Q3: 0.2 | R3: 0.21 | S3: 0.26 | T3: 0.25 | U3: 0.25 | V3: 0.28 | W3: 0.25 | X3: 0.25 | Y3: 0.24 | Z3: 0.24 | AC3: =AVERAGE(E3:Z3) -> 0.21454545
A4: Bolivia | C4: BOL | D4: Financial Development Index | E4: 0.11 | F4: 0.11 | G4: 0.12 | H4: 0.15 | I4: 0.15 | J4: 0.15 | K4: 0.16 | L4: 0.18 | M4: 0.18 | N4: 0.2 | O4: 0.2 | P4: 0.22 | Q4: 0.23 | R4: 0.24 | S4: 0.26 | T4: 0.28 | U4: 0.3 | V4: 0.31 | W4: 0.32 | X4: 0.33 | Y4: 0.35 | Z4: 0.39 | AC4: =AVERAGE(E4:Z4) -> 0.22454545
A5: Cameroon | C5: CMR | D5: Financial Development Index | E5: 0.08 | F5: 0.08 | G5: 0.08 | H5: 0.07 | I5: 0.07 | J5: 0.08 | K5: 0.08 | L5: 0.09 | M5: 0.09 | N5: 0.08 | O5: 0.08 | P5: 0.08 | Q5: 0.08 | R5: 0.1 | S5: 0.08 | T5: 0.08 | U5: 0.08 | V5: 0.09 | W5: 0.09 | X5: 0.09 | Y5: 0.09 | Z5: 0.1 | AC5: =AVERAGE(E5:Z5) -> 0.083636364
A6: Congo, Rep. of | C6: COG | D6: Financial Development Index | E6: 0.04 | F6: 0.05 | G6: 0.04 | H6: 0.06 | I6: 0.04 | J6: 0.03 | K6: 0.03 | L6: 0.03 | M6: 0.04 | N6: 0.08 | O6: 0.09 | P6: 0.08 | Q6: 0.09 | R6: 0.09 | S6: 0.1 | T6: 0.12 | U6: 0.12 | V6: 0.12 | W6: 0.1 | X6: 0.1 | Y6: 0.1 | Z6: 0.09 | AC6: =AVERAGE(E6:Z6) -> 0.074545455
A7: Côte d'Ivoire | C7: CIV | D7: Financial Development Index | E7: 0.14 | F7: 0.12 | G7: 0.1 | H7: 0.1 | I7: 0.11 | J7: 0.11 | K7: 0.13 | L7: 0.14 | M7: 0.14 | N7: 0.14 | O7: 0.15 | P7: 0.13 | Q7: 0.15 | R7: 0.16 | S7: 0.16 | T7: 0.17 | U7: 0.17 | V7: 0.17 | W7: 0.15 | X7: 0.14 | Y7: 0.13 | Z7: 0.13 | AC7: =AVERAGE(E7:Z7) -> 0.13818182
A8: Egypt, Arab Rep. of | C8: EGY | D8: Financial Development Index | E8: 0.3 | F8: 0.31 | G8: 0.33 | H8: 0.33 | I8: 0.34 | J8: 0.42 | K8: 0.37 | L8: 0.37 | M8: 0.43 | N8: 0.4 | O8: 0.32 | P8: 0.28 | Q8: 0.27 | R8: 0.26 | S8: 0.29 | T8: 0.27 | U8: 0.3 | V8: 0.29 | W8: 0.29 | X8: 0.3 | Y8: 0.3 | Z8: 0.31 | AC8: =AVERAGE(E8:Z8) -> 0.32181818
A9: Ghana | C9: GHA | D9: Financial Development Index | E9: 0.12 | F9: 0.12 | G9: 0.11 | H9: 0.12 | I9: 0.14 | J9: 0.12 | K9: 0.11 | L9: 0.12 | M9: 0.13 | N9: 0.11 | O9: 0.12 | P9: 0.13 | Q9: 0.15 | R9: 0.15 | S9: 0.16 | T9: 0.16 | U9: 0.17 | V9: 0.17 | W9: 0.17 | X9: 0.18 | Y9: 0.17 | Z9: 0.18 | AC9: =AVERAGE(E9:Z9) -> 0.14136364
A10: Haiti | C10: HTI | D10: Financial Development Index | E10: 0.09 | F10: 0.09 | G10: 0.09 | H10: 0.09 | I10: 0.09 | J10: 0.06 | K10: 0.06 | L10: 0.06 | M10: 0.06 | N10: 0.08 | O10: 0.08 | P10: 0.09 | Q10: 0.1 | R10: 0.1 | S10: 0.1 | T10: 0.1 | U10: 0.1 | V10: 0.1 | W10: 0.1 | X10: 0.1 | Y10: 0.09 | Z10: 0.1 | AC10: =AVERAGE(E10:Z10) -> 0.087727273
A11: Honduras | C11: HND | D11: Financial Development Index | E11: 0.13 | F11: 0.15 | G11: 0.14 | H11: 0.16 | I11: 0.15 | J11: 0.16 | K11: 0.18 | L11: 0.19 | M11: 0.2 | N11: 0.19 | O11: 0.18 | P11: 0.18 | Q11: 0.2 | R11: 0.2 | S11: 0.2 | T11: 0.2 | U11: 0.21 | V11: 0.21 | W11: 0.21 | X11: 0.21 | Y11: 0.21 | Z11: 0.21 | AC11: =AVERAGE(E11:Z11) -> 0.185
A12: India | C12: IND | D12: Financial Development Index | E12: 0.44 | F12: 0.42 | G12: 0.43 | H12: 0.43 | I12: 0.45 | J12: 0.45 | K12: 0.47 | L12: 0.45 | M12: 0.48 | N12: 0.51 | O12: 0.48 | P12: 0.44 | Q12: 0.42 | R12: 0.42 | S12: 0.44 | T12: 0.44 | U12: 0.45 | V12: 0.46 | W12: 0.47 | X12: 0.47 | Y12: 0.54 | Z12: 0.53 | AC12: =AVERAGE(E12:Z12) -> 0.45863636
A13: Jordan | C13: JOR | D13: Financial Development Index | E13: 0.53 | F13: 0.53 | G13: 0.53 | H13: 0.52 | I13: 0.53 | J13: 0.54 | K13: 0.5 | L13: 0.51 | M13: 0.58 | N13: 0.5 | O13: 0.46 | P13: 0.42 | Q13: 0.4 | R13: 0.39 | S13: 0.37 | T13: 0.37 | U13: 0.37 | V13: 0.37 | W13: 0.38 | X13: 0.36 | Y13: 0.35 | Z13: 0.36 | AC13: =AVERAGE(E13:Z13) -> 0.44863636
... A28: Zambia | C28: ZMB | D28: Financial Development Index | E28: 0.14 | F28: 0.14 | G28: 0.17 | H28: 0.14 | I28: 0.16 | J28: 0.15 | K28: 0.17 | L28: 0.18 | M28: 0.18 | N28: 0.16 | O28: 0.17 | P28: 0.19 | Q28: 0.19 | R28: 0.19 | S28: 0.18 | T28: 0.19 | U28: 0.19 | V28: 0.19 | W28: 0.19 | X28: 0.19 | Y28: 0.2 | Z28: 0.2 | AC28: =AVERAGE(E28:Z28) -> 0.17545455
A33: Source: | D33: https://data.imf.org/?sk=f8032e80-b36c-43b1-ac26-493c5b1cd33b&sid=1480712464593
D34: (International Monetary Fund)

Sheet FD all indicators
A1: Financial Development (FD)
C2: 2000 | D2: 2001 | E2: 2002 | F2: 2003 | G2: 2004 | H2: 2005 | I2: 2006 | J2: 2007 | K2: 2008 | L2: 2009 | M2: 2010 | N2: 2011 | O2: 2012 | P2: 2013 | Q2: 2014 | R2: 2015 | S2: 2016 | T2: 2017 | U2: 2018 | V2: 2019 | W2: 2020 | X2: 2021
A3: Angola | B3: Financial Development Index | C3: 0.09 | D3: 0.09 | E3: 0.1 | F3: 0.1 | G3: 0.11 | H3: 0.11 | I3: 0.12 | J3: 0.13 | K3: 0.14 | L3: 0.16 | M3: 0.15 | N3: 0.14 | O3: 0.13 | P3: 0.14 | Q3: 0.13 | R3: 0.15 | S3: 0.15 | T3: 0.15 | U3: 0.14 | V3: 0.1 | W3: 0.13 | X3: 0.14
B4: Financial Institutions Access Index | C4: 0.02 | D4: 0.02 | E4: 0.02 | F4: 0.02 | G4: 0.03 | H4: 0.03 | I4: 0.05 | J4: 0.06 | K4: 0.08 | L4: 0.1 | M4: 0.13 | N4: 0.15 | O4: 0.17 | P4: 0.19 | Q4: 0.2 | R4: 0.21 | S4: 0.2 | T4: 0.21 | U4: 0.19 | V4: 0.19 | W4: 0.18 | X4: 0.17
B5: Financial Institutions Depth Index | C5: 0.03 | D5: 0.03 | E5: 0.05 | F5: 0.06 | G5: 0.05 | H5: 0.05 | I5: 0.04 | J5: 0.04 | K5: 0.04 | L5: 0.07 | M5: 0.07 | N5: 0.06 | O5: 0.06 | P5: 0.06 | Q5: 0.06 | R5: 0.07 | S5: 0.06 | T5: 0.05 | U5: 0.04 | V5: 0.05 | W5: 0.04 | X5: 0.04
B6: Financial Institutions Efficiency Index | C6: 0.4 | D6: 0.38 | E6: 0.42 | F6: 0.4 | G6: 0.41 | H6: 0.42 | I6: 0.51 | J6: 0.61 | K6: 0.72 | L6: 0.7 | M6: 0.68 | N6: 0.61 | O6: 0.54 | P6: 0.56 | Q6: 0.46 | R6: 0.52 | S6: 0.56 | T6: 0.57 | U6: 0.57 | V6: 0.18 | W6: 0.36 | X6: 0.58
B7: Financial Institutions Index | C7: 0.13 | D7: 0.13 | E7: 0.14 | F7: 0.14 | G7: 0.14 | H7: 0.15 | I7: 0.18 | J7: 0.21 | K7: 0.25 | L7: 0.26 | M7: 0.27 | N7: 0.26 | O7: 0.25 | P7: 0.26 | Q7: 0.24 | R7: 0.26 | S7: 0.26 | T7: 0.26 | U7: 0.26 | V7: 0.15 | W7: 0.2 | X7: 0.25
B8: Financial Markets Access Index | C8: 0.01 | D8: 0.01 | E8: 0.01 | F8: 0.01 | G8: 0.01 | H8: 0.01 | I8: 0.01 | J8: 0.01 | K8: 0.01 | L8: 0.01 | M8: 0.01 | N8: 0.01 | O8: 0.01 | P8: 0.01 | Q8: 0.01 | R8: 0.01 | S8: 0.01 | T8: 0 | U8: 0 | V8: 0 | W8: 0.01 | X8: 0
B9: Financial Markets Depth Index | C9: 0.14 | D9: 0.15 | E9: 0.15 | F9: 0.15 | G9: 0.18 | H9: 0.15 | I9: 0.11 | J9: 0.09 | K9: 0.07 | L9: 0.1 | M9: 0.07 | N9: 0.05 | O9: 0.03 | P9: 0.05 | Q9: 0.06 | R9: 0.08 | S9: 0.09 | T9: 0.07 | U9: 0.07 | V9: 0.1 | W9: 0.16 | X9: 0.06
B10: Financial Markets Efficiency Index | C10: 0 | D10: 0 | E10: 0 | F10: 0 | G10: 0 | H10: 0 | I10: 0 | J10: 0 | K10: 0 | L10: 0 | M10: 0 | N10: 0 | O10: 0 | P10: 0 | Q10: 0 | R10: 0 | S10: 0 | T10: 0 | U10: 0 | V10: 0 | W10: 0 | X10: 0
B11: Financial Markets Index | C11: 0.06 | D11: 0.06 | E11: 0.06 | F11: 0.06 | G11: 0.07 | H11: 0.06 | I11: 0.05 | J11: 0.04 | K11: 0.03 | L11: 0.04 | M11: 0.03 | N11: 0.02 | O11: 0.01 | P11: 0.02 | Q11: 0.03 | R11: 0.03 | S11: 0.04 | T11: 0.03 | U11: 0.03 | V11: 0.04 | W11: 0.06 | X11: 0.02
A12: Bangladesh | B12: Financial Development Index | C12: 0.22 | D12: 0.19 | E12: 0.2 | F12: 0.21 | G12: 0.19 | H12: 0.16 | I12: 0.14 | J12: 0.15 | K12: 0.19 | L12: 0.2 | M12: 0.23 | N12: 0.21 | O12: 0.2 | P12: 0.21 | Q12: 0.26 | R12: 0.25 | S12: 0.25 | T12: 0.28 | U12: 0.25 | V12: 0.25 | W12: 0.24 | X12: 0.24
B13: Financial Institutions Access Index | C13: 0.08 | D13: 0.09 | E13: 0.09 | F13: 0.08 | G13: 0.08 | H13: 0.08 | I13: 0.09 | J13: 0.09 | K13: 0.09 | L13: 0.09 | M13: 0.1 | N13: 0.11 | O13: 0.11 | P13: 0.12 | Q13: 0.12 | R13: 0.13 | S13: 0.14 | T13: 0.14 | U13: 0.14 | V13: 0.15 | W13: 0.15 | X13: 0.16
B14: Financial Institutions Depth Index | C14: 0.05 | D14: 0.05 | E14: 0.06 | F14: 0.06 | G14: 0.07 | H14: 0.07 | I14: 0.08 | J14: 0.08 | K14: 0.08 | L14: 0.09 | M14: 0.1 | N14: 0.1 | O14: 0.1 | P14: 0.1 | Q14: 0.1 | R14: 0.1 | S14: 0.1 | T14: 0.1 | U14: 0.1 | V14: 0.1 | W14: 0.1 | X14: 0.1
B15: Financial Institutions Efficiency Index | C15: 0.53 | D15: 0.58 | E15: 0.56 | F15: 0.6 | G15: 0.46 | H15: 0.62 | I15: 0.44 | J15: 0.44 | K15: 0.63 | L15: 0.64 | M15: 0.64 | N15: 0.65 | O15: 0.54 | P15: 0.67 | Q15: 0.65 | R15: 0.64 | S15: 0.62 | T15: 0.64 | U15: 0.66 | V15: 0.66 | W15: 0.66 | X15: 0.66
B16: Financial Institutions Index | C16: 0.2 | D16: 0.22 | E16: 0.21 | F16: 0.23 | G16: 0.19 | H16: 0.24 | I16: 0.19 | J16: 0.19 | K16: 0.24 | L16: 0.25 | M16: 0.26 | N16: 0.27 | O16: 0.24 | P16: 0.27 | Q16: 0.27 | R16: 0.27 | S16: 0.27 | T16: 0.28 | U16: 0.28 | V16: 0.28 | W16: 0.29 | X16: 0.29
B17: Financial Markets Access Index | C17: 0.16 | D17: 0.16 | E17: 0.16 | F17: 0.15 | G17: 0.15 | H17: 0.15 | I17: 0.16 | J17: 0.16 | K17: 0.18 | L17: 0.25 | M17: 0.33 | N17: 0.31 | O17: 0.29 | P17: 0.28 | Q17: 0.3 | R17: 0.29 | S17: 0.3 | T17: 0.35 | U17: 0.3 | V17: 0.3 | W17: 0.3 | X17: 0.3
B18: Financial Markets Depth Index | C18: 0.02 | D18: 0.01 | E18: 0.07 | F18: 0.07 | G18: 0.07 | H18: 0.01 | I18: 0.02 | J18: 0.03 | K18: 0.04 | L18: 0.06 | M18: 0.11 | N18: 0.1 | O18: 0.1 | P18: 0.09 | Q18: 0.14 | R18: 0.11 | S18: 0.09 | T18: 0.11 | U18: 0.08 | V18: 0.07 | W18: 0.08 | X18: 0.08
B19: Financial Markets Efficiency Index | C19: 0.53 | D19: 0.33 | E19: 0.33 | F19: 0.33 | G19: 0.33 | H19: 0.08 | I19: 0.08 | J19: 0.1 | K19: 0.15 | L19: 0.14 | M19: 0.14 | N19: 0.06 | O19: 0.06 | P19: 0.03 | Q19: 0.29 | R19: 0.26 | S19: 0.27 | T19: 0.38 | U19: 0.26 | V19: 0.25 | W19: 0.21 | X19: 0.21
B20: Financial Markets Index | C20: 0.22 | D20: 0.16 | E20: 0.18 | F20: 0.18 | G20: 0.18 | H20: 0.08 | I20: 0.08 | J20: 0.1 | K20: 0.12 | L20: 0.15 | M20: 0.19 | N20: 0.15 | O20: 0.15 | P20: 0.13 | Q20: 0.24 | R20: 0.22 | S20: 0.21 | T20: 0.27 | U20: 0.21 | V20: 0.2 | W20: 0.19 | X20: 0.19
A21: Bolivia | B21: Financial Development Index | C21: 0.11 | D21: 0.11 | E21: 0.12 | F21: 0.15 | G21: 0.15 | H21: 0.15 | I21: 0.16 | J21: 0.18 | K21: 0.18 | L21: 0.2 | M21: 0.2 | N21: 0.22 | O21: 0.23 | P21: 0.24 | Q21: 0.26 | R21: 0.28 | S21: 0.3 | T21: 0.31 | U21: 0.32 | V21: 0.33 | W21: 0.35 | X21: 0.39
B22: Financial Institutions Access Index | C22: 0.08 | D22: 0.08 | E22: 0.09 | F22: 0.09 | G22: 0.1 | H22: 0.11 | I22: 0.12 | J22: 0.24 | K22: 0.25 | L22: 0.29 | M22: 0.33 | N22: 0.39 | O22: 0.42 | P22: 0.48 | Q22: 0.53 | R22: 0.57 | S22: 0.63 | T22: 0.65 | U22: 0.66 | V22: 0.68 | W22: 0.69 | X22: 0.69
B23: Financial Institutions Depth Index | C23: 0.21 | D23: 0.21 | E23: 0.24 | F23: 0.26 | G23: 0.25 | H23: 0.25 | I23: 0.22 | J23: 0.21 | K23: 0.22 | L23: 0.25 | M23: 0.25 | N23: 0.25 | O23: 0.26 | P23: 0.28 | Q23: 0.29 | R23: 0.34 | S23: 0.38 | T23: 0.38 | U23: 0.4 | V23: 0.42 | W23: 0.49 | X23: 0.69
B24: Financial Institutions Efficiency Index | C24: 0.3 | D24: 0.3 | E24: 0.31 | F24: 0.47 | G24: 0.47 | H24: 0.43 | I24: 0.58 | J24: 0.54 | K24: 0.53 | L24: 0.55 | M24: 0.53 | N24: 0.55 | O24: 0.56 | P24: 0.51 | Q24: 0.55 | R24: 0.54 | S24: 0.56 | T24: 0.58 | U24: 0.59 | V24: 0.59 | W24: 0.62 | X24: 0.6
B25: Financial Institutions Index | C25: 0.21 | D25: 0.21 | E25: 0.23 | F25: 0.28 | G25: 0.28 | H25: 0.27 | I25: 0.31 | J25: 0.34 | K25: 0.35 | L25: 0.38 | M25: 0.39 | N25: 0.43 | O25: 0.45 | P25: 0.46 | Q25: 0.5 | R25: 0.54 | S25: 0.59 | T25: 0.6 | U25: 0.61 | V25: 0.64 | W25: 0.68 | X25: 0.76
B26: Financial Markets Access Index | C26: 0.02 | D26: 0.02 | E26: 0.02 | F26: 0.02 | G26: 0.02 | H26: 0.02 | I26: 0.02 | J26: 0.02 | K26: 0.02 | L26: 0.02 | M26: 0.02 | N26: 0.02 | O26: 0.02 | P26: 0.02 | Q26: 0.02 | R26: 0.02 | S26: 0.02 | T26: 0.02 | U26: 0.02 | V26: 0.01 | W26: 0.01 | X26: 0.01
B27: Financial Markets Depth Index | C27: 0.01 | D27: 0.01 | E27: 0.01 | F27: 0.01 | G27: 0.02 | H27: 0.02 | I27: 0.02 | J27: 0.02 | K27: 0.01 | L27: 0.01 | M27: 0.01 | N27: 0.01 | O27: 0.01 | P27: 0.01 | Q27: 0.01 | R27: 0.01 | S27: 0.01 | T27: 0.01 | U27: 0.01 | V27: 0.01 | W27: 0.01 | X27: 0.02
B28: Financial Markets Efficiency Index | C28: 0 | D28: 0 | E28: 0 | F28: 0 | G28: 0 | H28: 0 | I28: 0 | J28: 0 | K28: 0 | L28: 0 | M28: 0 | N28: 0 | O28: 0 | P28: 0 | Q28: 0 | R28: 0 | S28: 0 | T28: 0 | U28: 0 | V28: 0 | W28: 0 | X28: 0
B29: Financial Markets Index | C29: 0.01 | D29: 0.01 | E29: 0.01 | F29: 0.01 | G29: 0.01 | H29: 0.01 | I29: 0.01 | J29: 0.01 | K29: 0.01 | L29: 0.01 | M29: 0.01 | N29: 0.01 | O29: 0.01 | P29: 0.01 | Q29: 0.01 | R29: 0.01 | S29: 0.01 | T29: 0.01 | U29: 0.01 | V29: 0.01 | W29: 0.01 | X29: 0.01
A30: Cambodia | B30: Financial Development Index | C30: 0.06 | D30: 0.03 | E30: 0.07 | F30: 0.08 | G30: 0.07 | H30: 0.07 | I30: 0.09 | J30: 0.1 | K30: 0.1 | L30: 0.09 | M30: 0.1 | N30: 0.11 | O30: 0.12 | P30: 0.13 | Q30: 0.14 | R30: 0.15 | S30: 0.15 | T30: 0.16 | U30: 0.17 | V30: 0.18 | W30: 0.2 | X30: 0.21
B31: Financial Institutions Access Index | C31: 0 | D31: 0 | E31: 0 | F31: 0 | G31: 0 | H31: 0 | I31: 0.03 | J31: 0.04 | K31: 0.05 | L31: 0.07 | M31: 0.07 | N31: 0.08 | O31: 0.08 | P31: 0.09 | Q31: 0.11 | R31: 0.13 | S31: 0.15 | T31: 0.16 | U31: 0.18 | V31: 0.2 | W31: 0.25 | X31: 0.28
B32: Financial Institutions Depth Index | C32: 0.02 | D32: 0.02 | E32: 0.02 | F32: 0.02 | G32: 0.02 | H32: 0.02 | I32: 0.03 | J32: 0.04 | K32: 0.05 | L32: 0.05 | M32: 0.06 | N32: 0.06 | O32: 0.08 | P32: 0.11 | Q32: 0.13 | R32: 0.16 | S32: 0.18 | T32: 0.19 | U32: 0.22 | V32: 0.26 | W32: 0.28 | X32: 0.28
B33: Financial Institutions Efficiency Index | C33: 0.37 | D33: 0.17 | E33: 0.48 | F33: 0.51 | G33: 0.5 | H33: 0.47 | I33: 0.52 | J33: 0.56 | K33: 0.53 | L33: 0.47 | M33: 0.5 | N33: 0.53 | O33: 0.55 | P33: 0.56 | Q33: 0.57 | R33: 0.57 | S33: 0.57 | T33: 0.58 | U33: 0.56 | V33: 0.6 | W33: 0.59 | X33: 0.61
B34: Financial Institutions Index | C34: 0.11 | D34: 0.05 | E34: 0.14 | F34: 0.15 | G34: 0.15 | H34: 0.14 | I34: 0.17 | J34: 0.19 | K34: 0.19 | L34: 0.18 | M34: 0.19 | N34: 0.2 | O34: 0.22 | P34: 0.24 | Q34: 0.26 | R34: 0.28 | S34: 0.3 | T34: 0.31 | U34: 0.32 | V34: 0.36 | W34: 0.39 | X34: 0.41
B35: Financial Markets Access Index | C35: 0 | D35: 0 | E35: 0 | F35: 0 | G35: 0 | H35: 0 | I35: 0 | J35: 0 | K35: 0 | L35: 0 | M35: 0 | N35: 0 | O35: 0 | P35: 0 | Q35: 0 | R35: 0 | S35: 0 | T35: 0 | U35: 0 | V35: 0 | W35: 0 | X35: 0
B36: Financial Markets Depth Index | C36: 0 | D36: 0 | E36: 0 | F36: 0 | G36: 0 | H36: 0 | I36: 0 | J36: 0 | K36: 0.01 | L36: 0.01 | M36: 0.03 | N36: 0.04 | O36: 0.03 | P36: 0.03 | Q36: 0.02 | R36: 0.02 | S36: 0.02 | T36: 0.02 | U36: 0.01 | V36: 0 | W36: 0 | X36: 0
B37: Financial Markets Efficiency Index | C37: 0 | D37: 0 | E37: 0 | F37: 0 | G37: 0 | H37: 0 | I37: 0 | J37: 0 | K37: 0 | L37: 0 | M37: 0 | N37: 0 | O37: 0 | P37: 0 | Q37: 0 | R37: 0 | S37: 0 | T37: 0 | U37: 0 | V37: 0 | W37: 0 | X37: 0
B38: Financial Markets Index | C38: 0 | D38: 0 | E38: 0 | F38: 0 | G38: 0 | H38: 0 | I38: 0 | J38: 0 | K38: 0 | L38: 0 | M38: 0.01 | N38: 0.01 | O38: 0.01 | P38: 0.01 | Q38: 0.01 | R38: 0.01 | S38: 0.01 | T38: 0.01 | U38: 0 | V38: 0 | W38: 0 | X38: 0
A39: Cameroon | B39: Financial Development Index | C39: 0.08 | D39: 0.08 | E39: 0.08 | F39: 0.07 | G39: 0.07 | H39: 0.08 | I39: 0.08 | J39: 0.09 | K39: 0.09 | L39: 0.08 | M39: 0.08 | N39: 0.08 | O39: 0.08 | P39: 0.1 | Q39: 0.08 | R39: 0.08 | S39: 0.08 | T39: 0.09 | U39: 0.09 | V39: 0.09 | W39: 0.09 | X39: 0.1
B40: Financial Institutions Access Index | C40: 0.01 | D40: 0.01 | E40: 0.01 | F40: 0.01 | G40: 0.01 | H40: 0.01 | I40: 0.02 | J40: 0.02 | K40: 0.02 | L40: 0.02 | M40: 0.03 | N40: 0.03 | O40: 0.03 | P40: 0.04 | Q40: 0.04 | R40: 0.04 | S40: 0.04 | T40: 0.04 | U40: 0.05 | V40: 0.05 | W40: 0.05 | X40: 0.05
B41: Financial Institutions Depth Index | C41: 0.04 | D41: 0.04 | E41: 0.04 | F41: 0.04 | G41: 0.04 | H41: 0.04 | I41: 0.04 | J41: 0.04 | K41: 0.04 | L41: 0.04 | M41: 0.05 | N41: 0.05 | O41: 0.05 | P41: 0.05 | Q41: 0.05 | R41: 0.05 | S41: 0.06 | T41: 0.05 | U41: 0.06 | V41: 0.05 | W41: 0.05 | X41: 0.05
B42: Financial Institutions Efficiency Index | C42: 0.53 | D42: 0.53 | E42: 0.49 | F42: 0.45 | G42: 0.46 | H42: 0.49 | I42: 0.49 | J42: 0.52 | K42: 0.51 | L42: 0.5 | M42: 0.45 | N42: 0.45 | O42: 0.43 | P42: 0.55 | Q42: 0.41 | R42: 0.43 | S42: 0.42 | T42: 0.46 | U42: 0.46 | V42: 0.48 | W42: 0.45 | X42: 0.56
B43: Financial Institutions Index | C43: 0.16 | D43: 0.16 | E43: 0.15 | F43: 0.14 | G43: 0.14 | H43: 0.16 | I43: 0.16 | J43: 0.17 | K43: 0.17 | L43: 0.16 | M43: 0.15 | N43: 0.16 | O43: 0.15 | P43: 0.19 | Q43: 0.15 | R43: 0.16 | S43: 0.16 | T43: 0.17 | U43: 0.17 | V43: 0.17 | W43: 0.16 | X43: 0.2
B44: Financial Markets Access Index | C44: 0 | D44: 0 | E44: 0 | F44: 0 | G44: 0 | H44: 0 | I44: 0 | J44: 0 | K44: 0 | L44: 0 | M44: 0 | N44: 0 | O44: 0 | P44: 0 | Q44: 0 | R44: 0 | S44: 0 | T44: 0 | U44: 0 | V44: 0 | W44: 0 | X44: 0
B45: Financial Markets Depth Index | C45: 0 | D45: 0 | E45: 0 | F45: 0 | G45: 0 | H45: 0 | I45: 0 | J45: 0 | K45: 0 | L45: 0 | M45: 0 | N45: 0.01 | O45: 0.01 | P45: 0.01 | Q45: 0.01 | R45: 0.01 | S45: 0.01 | T45: 0.01 | U45: 0.01 | V45: 0.01 | W45: 0.01 | X45: 0.01
B46: Financial Markets Efficiency Index | C46: 0 | D46: 0 | E46: 0 | F46: 0 | G46: 0 | H46: 0 | I46: 0 | J46: 0 | K46: 0 | L46: 0 | M46: 0 | N46: 0 | O46: 0 | P46: 0 | Q46: 0 | R46: 0 | S46: 0 | T46: 0 | U46: 0 | V46: 0 | W46: 0 | X46: 0
B47: Financial Markets Index | C47: 0 | D47: 0 | E47: 0 | F47: 0 | G47: 0 | H47: 0 | I47: 0 | J47: 0 | K47: 0 | L47: 0 | M47: 0 | N47: 0 | O47: 0 | P47: 0 | Q47: 0 | R47: 0 | S47: 0 | T47: 0 | U47: 0 | V47: 0 | W47: 0 | X47: 0
A48: Congo, Rep. of | B48: Financial Development Index | C48: 0.04 | D48: 0.05 | E48: 0.04 | F48: 0.06 | G48: 0.04 | H48: 0.03 | I48: 0.03 | J48: 0.03 | K48: 0.04 | L48: 0.08 | M48: 0.09 | N48: 0.08 | O48: 0.09 | P48: 0.09 | Q48: 0.1 | R48: 0.12 | S48: 0.12 | T48: 0.12 | U48: 0.1 | V48: 0.1 | W48: 0.1 | X48: 0.09
B49: Financial Institutions Access Index | C49: 0 | D49: 0 | E49: 0 | F49: 0 | G49: 0 | H49: 0 | I49: 0 | J49: 0 | K49: 0 | L49: 0 | M49: 0 | N49: 0.01 | O49: 0.01 | P49: 0.04 | Q49: 0.05 | R49: 0.06 | S49: 0.07 | T49: 0.08 | U49: 0.09 | V49: 0.09 | W49: 0.09 | X49: 0.09
B50: Financial Institutions Depth Index | C50: 0.01 | D50: 0.02 | E50: 0.02 | F50: 0.05 | G50: 0.03 | H50: 0.02 | I50: 0.02 | J50: 0.02 | K50: 0.03 | L50: 0.04 | M50: 0.03 | N50: 0.03 | O50: 0.03 | P50: 0.04 | Q50: 0.05 | R50: 0.07 | S50: 0.07 | T50: 0.06 | U50: 0.05 | V50: 0.05 | W50: 0.06 | X50: 0.06
B51: Financial Institutions Efficiency Index | C51: 0.18 | D51: 0.19 | E51: 0.2 | F51: 0.24 | G51: 0.19 | H51: 0.13 | I51: 0.12 | J51: 0.14 | K51: 0.18 | L51: 0.47 | M51: 0.54 | N51: 0.51 | O51: 0.53 | P51: 0.5 | Q51: 0.5 | R51: 0.5 | S51: 0.5 | T51: 0.49 | U51: 0.41 | V51: 0.41 | W51: 0.45 | X51: 0.38
B52: Financial Institutions Index | C52: 0.06 | D52: 0.06 | E52: 0.06 | F52: 0.09 | G52: 0.06 | H52: 0.04 | I52: 0.04 | J52: 0.05 | K52: 0.06 | L52: 0.14 | M52: 0.16 | N52: 0.16 | O52: 0.16 | P52: 0.17 | Q52: 0.18 | R52: 0.19 | S52: 0.19 | T52: 0.19 | U52: 0.17 | V52: 0.17 | W52: 0.19 | X52: 0.16
B53: Financial Markets Access Index | C53: 0 | D53: 0 | E53: 0 | F53: 0 | G53: 0 | H53: 0 | I53: 0 | J53: 0 | K53: 0 | L53: 0 | M53: 0 | N53: 0 | O53: 0 | P53: 0 | Q53: 0 | R53: 0 | S53: 0 | T53: 0 | U53: 0 | V53: 0 | W53: 0 | X53: 0
B54: Financial Markets Depth Index | C54: 0.05 | D54: 0.09 | E54: 0.06 | F54: 0.07 | G54: 0.06 | H54: 0.05 | I54: 0.02 | J54: 0.02 | K54: 0.02 | L54: 0.02 | M54: 0.02 | N54: 0.02 | O54: 0.02 | P54: 0.02 | Q54: 0.05 | R54: 0.09 | S54: 0.1 | T54: 0.1 | U54: 0.08 | V54: 0.05 | W54: 0.05 | X54: 0.05
B55: Financial Markets Efficiency Index | C55: 0 | D55: 0 | E55: 0 | F55: 0 | G55: 0 | H55: 0 | I55: 0 | J55: 0 | K55: 0 | L55: 0 | M55: 0 | N55: 0 | O55: 0 | P55: 0 | Q55: 0 | R55: 0 | S55: 0 | T55: 0 | U55: 0 | V55: 0 | W55: 0 | X55: 0
B56: Financial Markets Index | C56: 0.02 | D56: 0.03 | E56: 0.02 | F56: 0.03 | G56: 0.02 | H56: 0.02 | I56: 0.01 | J56: 0.01 | K56: 0.01 | L56: 0.01 | M56: 0.01 | N56: 0.01 | O56: 0.01 | P56: 0.01 | Q56: 0.02 | R56: 0.03 | S56: 0.04 | T56: 0.04 | U56: 0.03 | V56: 0.02 | W56: 0.02 | X56: 0.02
A57: Côte d'Ivoire | B57: Financial Development Index | C57: 0.14 | D57: 0.12 | E57: 0.1 | F57: 0.1 | G57: 0.11 | H57: 0.11 | I57: 0.13 | J57: 0.14 | K57: 0.14 | L57: 0.14 | M57: 0.15 | N57: 0.13 | O57: 0.15 | P57: 0.16 | Q57: 0.16 | R57: 0.17 | S57: 0.17 | T57: 0.17 | U57: 0.15 | V57: 0.14 | W57: 0.13 | X57: 0.13
B58: Financial Institutions Access Index | C58: 0.03 | D58: 0.03 | E58: 0.03 | F58: 0.02 | G58: 0.03 | H58: 0.03 | I58: 0.03 | J58: 0.03 | K58: 0.05 | L58: 0.05 | M58: 0.08 | N58: 0.08 | O58: 0.09 | P58: 0.08 | Q58: 0.09 | R58: 0.09 | S58: 0.09 | T58: 0.09 | U58: 0.09 | V58: 0.09 | W58: 0.09 | X58: 0.09
B59: Financial Institutions Depth Index | C59: 0.04 | D59: 0.04 | E59: 0.04 | F59: 0.04 | G59: 0.04 | H59: 0.04 | I59: 0.04 | J59: 0.04 | K59: 0.04 | L59: 0.04 | M59: 0.05 | N59: 0.04 | O59: 0.04 | P59: 0.04 | Q59: 0.04 | R59: 0.03 | S59: 0.03 | T59: 0.03 | U59: 0.03 | V59: 0.03 | W59: 0.03 | X59: 0.04
B60: Financial Institutions Efficiency Index | C60: 0.4 | D60: 0.38 | E60: 0.32 | F60: 0.28 | G60: 0.34 | H60: 0.31 | I60: 0.39 | J60: 0.41 | K60: 0.41 | L60: 0.4 | M60: 0.43 | N60: 0.33 | O60: 0.41 | P60: 0.43 | Q60: 0.48 | R60: 0.49 | S60: 0.51 | T60: 0.52 | U60: 0.53 | V60: 0.53 | W60: 0.53 | X60: 0.56
B61: Financial Institutions Index | C61: 0.14 | D61: 0.13 | E61: 0.11 | F61: 0.1 | G61: 0.12 | H61: 0.11 | I61: 0.14 | J61: 0.14 | K61: 0.15 | L61: 0.15 | M61: 0.17 | N61: 0.14 | O61: 0.17 | P61: 0.17 | Q61: 0.18 | R61: 0.18 | S61: 0.19 | T61: 0.19 | U61: 0.2 | V61: 0.2 | W61: 0.2 | X61: 0.2
B62: Financial Markets Access Index | C62: 0.01 | D62: 0.01 | E62: 0.01 | F62: 0.01 | G62: 0.01 | H62: 0.01 | I62: 0.01 | J62: 0.01 | K62: 0.01 | L62: 0.01 | M62: 0.01 | N62: 0.01 | O62: 0.01 | P62: 0.01 | Q62: 0.01 | R62: 0.01 | S62: 0.01 | T62: 0.01 | U62: 0.01 | V62: 0.01 | W62: 0.01 | X62: 0.01
B63: Financial Markets Depth Index | C63: 0.26 | D63: 0.25 | E63: 0.21 | F63: 0.24 | G63: 0.22 | H63: 0.22 | I63: 0.25 | J63: 0.32 | K63: 0.3 | L63: 0.29 | M63: 0.3 | N63: 0.29 | O63: 0.29 | P63: 0.32 | Q63: 0.3 | R63: 0.32 | S63: 0.32 | T63: 0.32 | U63: 0.22 | V63: 0.17 | W63: 0.14 | X63: 0.1
B64: Financial Markets Efficiency Index | C64: 0.09 | D64: 0.01 | E64: 0.02 | F64: 0.02 | G64: 0.03 | H64: 0.02 | I64: 0.03 | J64: 0.02 | K64: 0.05 | L64: 0.05 | M64: 0.04 | N64: 0.02 | O64: 0.02 | P64: 0.04 | Q64: 0.04 | R64: 0.05 | S64: 0.07 | T64: 0.07 | U64: 0.07 | V64: 0.02 | W64: 0.02 | X64: 0.02
B65: Financial Markets Index | C65: 0.13 | D65: 0.1 | E65: 0.09 | F65: 0.1 | G65: 0.1 | H65: 0.09 | I65: 0.11 | J65: 0.13 | K65: 0.13 | L65: 0.13 | M65: 0.13 | N65: 0.12 | O65: 0.12 | P65: 0.14 | Q65: 0.13 | R65: 0.14 | S65: 0.14 | T65: 0.14 | U65: 0.1 | V65: 0.07 | W65: 0.06 | X65: 0.05
A66: Egypt, Arab Rep. of | B66: Financial Development Index | C66: 0.3 | D66: 0.31 | E66: 0.33 | F66: 0.33 | G66: 0.34 | H66: 0.42 | I66: 0.37 | J66: 0.37 | K66: 0.43 | L66: 0.4 | M66: 0.32 | N66: 0.28 | O66: 0.27 | P66: 0.26 | Q66: 0.29 | R66: 0.27 | S66: 0.3 | T66: 0.29 | U66: 0.29 | V66: 0.3 | W66: 0.3 | X66: 0.31
B67: Financial Institutions Access Index | C67: 0.06 | D67: 0.06 | E67: 0.06 | F67: 0.06 | G67: 0.06 | H67: 0.06 | I67: 0.07 | J67: 0.07 | K67: 0.08 | L67: 0.09 | M67: 0.09 | N67: 0.09 | O67: 0.1 | P67: 0.1 | Q67: 0.11 | R67: 0.11 | S67: 0.12 | T67: 0.14 | U67: 0.14 | V67: 0.17 | W67: 0.18 | X67: 0.2
B68: Financial Institutions Depth Index | C68: 0.13 | D68: 0.13 | E68: 0.14 | F68: 0.14 | G68: 0.14 | H68: 0.14 | I68: 0.13 | J68: 0.13 | K68: 0.12 | L68: 0.11 | M68: 0.1 | N68: 0.09 | O68: 0.09 | P68: 0.08 | Q68: 0.08 | R68: 0.08 | S68: 0.1 | T68: 0.09 | U68: 0.08 | V68: 0.08 | W68: 0.08 | X68: 0.08
B69: Financial Institutions Efficiency Index | C69: 0.65 | D69: 0.65 | E69: 0.63 | F69: 0.62 | G69: 0.61 | H69: 0.62 | I69: 0.58 | J69: 0.64 | K69: 0.67 | L69: 0.65 | M69: 0.69 | N69: 0.69 | O69: 0.69 | P69: 0.7 | Q69: 0.72 | R69: 0.75 | S69: 0.74 | T69: 0.71 | U69: 0.72 | V69: 0.73 | W69: 0.73 | X69: 0.73
B70: Financial Institutions Index | C70: 0.26 | D70: 0.26 | E70: 0.25 | F70: 0.25 | G70: 0.25 | H70: 0.25 | I70: 0.24 | J70: 0.26 | K70: 0.27 | L70: 0.26 | M70: 0.27 | N70: 0.27 | O70: 0.27 | P70: 0.27 | Q70: 0.28 | R70: 0.29 | S70: 0.3 | T70: 0.29 | U70: 0.29 | V70: 0.3 | W70: 0.31 | X70: 0.32
B71: Financial Markets Access Index | C71: 0.26 | D71: 0.27 | E71: 0.31 | F71: 0.3 | G71: 0.32 | H71: 0.36 | I71: 0.33 | J71: 0.33 | K71: 0.32 | L71: 0.26 | M71: 0.29 | N71: 0.31 | O71: 0.32 | P71: 0.33 | Q71: 0.31 | R71: 0.3 | S71: 0.34 | T71: 0.32 | U71: 0.31 | V71: 0.45 | W71: 0.3 | X71: 0.31
B72: Financial Markets Depth Index | C72: 0.29 | D72: 0.3 | E72: 0.34 | F72: 0.33 | G72: 0.37 | H72: 0.56 | I72: 0.46 | J72: 0.51 | K72: 0.43 | L72: 0.33 | M72: 0.22 | N72: 0.13 | O72: 0.13 | P72: 0.12 | Q72: 0.14 | R72: 0.1 | S72: 0.09 | T72: 0.14 | U72: 0.12 | V72: 0.11 | W72: 0.1 | X72: 0.1
B73: Financial Markets Efficiency Index | C73: 0.45 | D73: 0.47 | E73: 0.53 | F73: 0.52 | G73: 0.56 | H73: 0.78 | I73: 0.64 | J73: 0.55 | K73: 1 | L73: 1 | M73: 0.55 | N73: 0.4 | O73: 0.36 | P73: 0.26 | Q73: 0.47 | R73: 0.33 | S73: 0.48 | T73: 0.38 | U73: 0.43 | V73: 0.31 | W73: 0.48 | X73: 0.48
B74: Financial Markets Index | C74: 0.33 | D74: 0.35 | E74: 0.39 | F74: 0.38 | G74: 0.42 | H74: 0.57 | I74: 0.48 | J74: 0.47 | K74: 0.58 | L74: 0.53 | M74: 0.35 | N74: 0.27 | O74: 0.26 | P74: 0.23 | Q74: 0.3 | R74: 0.24 | S74: 0.29 | T74: 0.27 | U74: 0.28 | V74: 0.28 | W74: 0.29 | X74: 0.29
A75: Eswatini, Kingdom of | B75: Financial Development Index | C75: 0.11 | D75: 0.12 | E75: 0.1 | F75: 0.1 | G75: 0.12 | H75: 0.12 | I75: 0.13 | J75: 0.13 | K75: 0.15 | L75: 0.14 | M75: 0.14 | N75: 0.15 | O75: 0.15 | P75: 0.15 | Q75: 0.16 | R75: 0.16 | S75: 0.16 | T75: 0.15 | U75: 0.17 | V75: 0.16 | W75: 0.16 | X75: 0.18
B76: Financial Institutions Access Index | C76: 0.11 | D76: 0.1 | E76: 0.09 | F76: 0.1 | G76: 0.1 | H76: 0.13 | I76: 0.14 | J76: 0.15 | K76: 0.16 | L76: 0.17 | M76: 0.18 | N76: 0.2 | O76: 0.21 | P76: 0.22 | Q76: 0.25 | R76: 0.26 | S76: 0.25 | T76: 0.24 | U76: 0.26 | V76: 0.24 | W76: 0.25 | X76: 0.26
B77: Financial Institutions Depth Index | C77: 0.06 | D77: 0.05 | E77: 0.06 | F77: 0.07 | G77: 0.14 | H77: 0.08 | I77: 0.08 | J77: 0.09 | K77: 0.09 | L77: 0.09 | M77: 0.1 | N77: 0.11 | O77: 0.1 | P77: 0.1 | Q77: 0.13 | R77: 0.11 | S77: 0.12 | T77: 0.11 | U77: 0.15 | V77: 0.15 | W77: 0.16 | X77: 0.16
B78: Financial Institutions Efficiency Index | C78: 0.48 | D78: 0.51 | E78: 0.46 | F78: 0.45 | G78: 0.48 | H78: 0.5 | I78: 0.54 | J78: 0.55 | K78: 0.6 | L78: 0.55 | M78: 0.55 | N78: 0.56 | O78: 0.52 | P78: 0.54 | Q78: 0.54 | R78: 0.55 | S78: 0.49 | T78: 0.49 | U78: 0.55 | V78: 0.49 | W78: 0.46 | X78: 0.61
B79: Financial Institutions Index | C79: 0.2 | D79: 0.2 | E79: 0.19 | F79: 0.2 | G79: 0.24 | H79: 0.23 | I79: 0.24 | J79: 0.25 | K79: 0.27 | L79: 0.26 | M79: 0.27 | N79: 0.28 | O79: 0.28 | P79: 0.28 | Q79: 0.31 | R79: 0.31 | S79: 0.3 | T79: 0.28 | U79: 0.33 | V79: 0.3 | W79: 0.3 | X79: 0.35
B80: Financial Markets Access Index | C80: 0 | D80: 0 | E80: 0 | F80: 0 | G80: 0 | H80: 0 | I80: 0 | J80: 0 | K80: 0 | L80: 0 | M80: 0 | N80: 0 | O80: 0 | P80: 0 | Q80: 0 | R80: 0 | S80: 0 | T80: 0 | U80: 0 | V80: 0 | W80: 0 | X80: 0
B81: Financial Markets Depth Index | C81: 0.01 | D81: 0.02 | E81: 0.02 | F81: 0.02 | G81: 0.02 | H81: 0.01 | I81: 0.01 | J81: 0.02 | K81: 0.02 | L81: 0.02 | M81: 0.02 | N81: 0.02 | O81: 0.02 | P81: 0.02 | Q81: 0.02 | R81: 0.02 | S81: 0.02 | T81: 0.02 | U81: 0.02 | V81: 0.02 | W81: 0.02 | X81: 0.02
B82: Financial Markets Efficiency Index | C82: 0 | D82: 0.08 | E82: 0 | F82: 0 | G82: 0 | H82: 0 | I82: 0 | J82: 0.02 | K82: 0.02 | L82: 0.02 | M82: 0.02 | N82: 0.02 | O82: 0.02 | P82: 0.02 | Q82: 0.02 | R82: 0.02 | S82: 0.02 | T82: 0.02 | U82: 0.02 | V82: 0.02 | W82: 0.02 | X82: 0.02
B83: Financial Markets Index | C83: 0 | D83: 0.03 | E83: 0.01 | F83: 0.01 | G83: 0.01 | H83: 0.01 | I83: 0.01 | J83: 0.01 | K83: 0.01 | L83: 0.01 | M83: 0.01 | N83: 0.01 | O83: 0.01 | P83: 0.01 | Q83: 0.01 | R83: 0.01 | S83: 0.01 | T83: 0.01 | U83: 0.01 | V83: 0.01 | W83: 0.01 | X83: 0.01
A84: Ghana | B84: Financial Development Index | C84: 0.12 | D84: 0.12 | E84: 0.11 | F84: 0.12 | G84: 0.14 | H84: 0.12 | I84: 0.11 | J84: 0.12 | K84: 0.13 | L84: 0.11 | M84: 0.12 | N84: 0.13 | O84: 0.15 | P84: 0.15 | Q84: 0.16 | R84: 0.16 | S84: 0.17 | T84: 0.17 | U84: 0.17 | V84: 0.18 | W84: 0.17 | X84: 0.18
B85: Financial Institutions Access Index | C85: 0.05 | D85: 0.04 | E85: 0.04 | F85: 0.04 | G85: 0.05 | H85: 0.05 | I85: 0.05 | J85: 0.07 | K85: 0.07 | L85: 0.08 | M85: 0.08 | N85: 0.08 | O85: 0.09 | P85: 0.1 | Q85: 0.1 | R85: 0.13 | S85: 0.13 | T85: 0.15 | U85: 0.15 | V85: 0.15 | W85: 0.12 | X85: 0.19
B86: Financial Institutions Depth Index | C86: 0.04 | D86: 0.03 | E86: 0.04 | F86: 0.04 | G86: 0.04 | H86: 0.05 | I86: 0.04 | J86: 0.05 | K86: 0.05 | L86: 0.06 | M86: 0.06 | N86: 0.06 | O86: 0.06 | P86: 0.07 | Q86: 0.07 | R86: 0.08 | S86: 0.08 | T86: 0.08 | U86: 0.07 | V86: 0.08 | W86: 0.08 | X86: 0.09
B87: Financial Institutions Efficiency Index | C87: 0.5 | D87: 0.5 | E87: 0.47 | F87: 0.43 | G87: 0.43 | H87: 0.39 | I87: 0.36 | J87: 0.36 | K87: 0.32 | L87: 0.3 | M87: 0.34 | N87: 0.37 | O87: 0.46 | P87: 0.46 | Q87: 0.47 | R87: 0.41 | S87: 0.41 | T87: 0.42 | U87: 0.42 | V87: 0.44 | W87: 0.46 | X87: 0.47
B88: Financial Institutions Index | C88: 0.17 | D88: 0.17 | E88: 0.16 | F88: 0.15 | G88: 0.15 | H88: 0.15 | I88: 0.14 | J88: 0.15 | K88: 0.14 | L88: 0.14 | M88: 0.15 | N88: 0.16 | O88: 0.19 | P88: 0.2 | Q88: 0.2 | R88: 0.2 | S88: 0.2 | T88: 0.21 | U88: 0.21 | V88: 0.22 | W88: 0.21 | X88: 0.25
B89: Financial Markets Access Index | C89: 0.1 | D89: 0.11 | E89: 0.1 | F89: 0.11 | G89: 0.13 | H89: 0.13 | I89: 0.13 | J89: 0.14 | K89: 0.16 | L89: 0.17 | M89: 0.18 | N89: 0.17 | O89: 0.16 | P89: 0.15 | Q89: 0.16 | R89: 0.18 | S89: 0.18 | T89: 0.19 | U89: 0.18 | V89: 0.21 | W89: 0.23 | X89: 0.23
B90: Financial Markets Depth Index | C90: 0.05 | D90: 0.04 | E90: 0.02 | F90: 0.05 | G90: 0.05 | H90: 0.04 | I90: 0.03 | J90: 0.06 | K90: 0.06 | L90: 0.06 | M90: 0.06 | N90: 0.05 | O90: 0.05 | P90: 0.05 | Q90: 0.07 | R90: 0.08 | S90: 0.1 | T90: 0.07 | U90: 0.07 | V90: 0.09 | W90: 0.1 | X90: 0.08
B91: Financial Markets Efficiency Index | C91: 0.02 | D91: 0.06 | E91: 0.04 | F91: 0.08 | G91: 0.19 | H91: 0.1 | I91: 0.08 | J91: 0.07 | K91: 0.12 | L91: 0.03 | M91: 0.04 | N91: 0.1 | O91: 0.1 | P91: 0.1 | Q91: 0.1 | R91: 0.1 | S91: 0.1 | T91: 0.1 | U91: 0.1 | V91: 0.1 | W91: 0 | X91: 0
B92: Financial Markets Index | C92: 0.06 | D92: 0.07 | E92: 0.05 | F92: 0.08 | G92: 0.12 | H92: 0.09 | I92: 0.08 | J92: 0.09 | K92: 0.11 | L92: 0.09 | M92: 0.09 | N92: 0.11 | O92: 0.1 | P92: 0.1 | Q92: 0.11 | R92: 0.12 | S92: 0.13 | T92: 0.12 | U92: 0.11 | V92: 0.13 | W92: 0.11 | X92: 0.1
A93: Haiti | B93: Financial Development Index | C93: 0.09 | D93: 0.09 | E93: 0.09 | F93: 0.09 | G93: 0.09 | H93: 0.06 | I93: 0.06 | J93: 0.06 | K93: 0.06 | L93: 0.08 | M93: 0.08 | N93: 0.09 | O93: 0.1 | P93: 0.1 | Q93: 0.1 | R93: 0.1 | S93: 0.1 | T93: 0.1 | U93: 0.1 | V93: 0.1 | W93: 0.09 | X93: 0.1
B94: Financial Institutions Access Index | C94: 0.05 | D94: 0.04 | E94: 0.05 | F94: 0.05 | G94: 0.04 | H94: 0.04 | I94: 0.04 | J94: 0.04 | K94: 0.04 | L94: 0.04 | M94: 0.03 | N94: 0.04 | O94: 0.04 | P94: 0.04 | Q94: 0.04 | R94: 0.04 | S94: 0.04 | T94: 0.04 | U94: 0.04 | V94: 0.05 | W94: 0.05 | X94: 0.05
B95: Financial Institutions Depth Index | C95: 0.03 | D95: 0.03 | E95: 0.04 | F95: 0.04 | G95: 0.03 | H95: 0.03 | I95: 0.03 | J95: 0.03 | K95: 0.03 | L95: 0.03 | M95: 0.03 | N95: 0.03 | O95: 0.04 | P95: 0.04 | Q95: 0.05 | R95: 0.04 | S95: 0.04 | T95: 0.04 | U95: 0.04 | V95: 0.04 | W95: 0.04 | X95: 0.04
B96: Financial Institutions Efficiency Index | C96: 0.53 | D96: 0.53 | E96: 0.53 | F96: 0.53 | G96: 0.53 | H96: 0.32 | I96: 0.32 | J96: 0.32 | K96: 0.32 | L96: 0.44 | M96: 0.47 | N96: 0.57 | O96: 0.6 | P96: 0.61 | Q96: 0.58 | R96: 0.58 | S96: 0.59 | T96: 0.58 | U96: 0.59 | V96: 0.59 | W96: 0.51 | X96: 0.57
B97: Financial Institutions Index | C97: 0.18 | D97: 0.18 | E97: 0.18 | F97: 0.18 | G97: 0.17 | H97: 0.12 | I97: 0.12 | J97: 0.12 | K97: 0.12 | L97: 0.15 | M97: 0.15 | N97: 0.18 | O97: 0.19 | P97: 0.2 | Q97: 0.19 | R97: 0.19 | S97: 0.19 | T97: 0.19 | U97: 0.2 | V97: 0.2 | W97: 0.17 | X97: 0.19
B98: Financial Markets Access Index | C98: 0 | D98: 0 | E98: 0 | F98: 0 | G98: 0 | H98: 0 | I98: 0 | J98: 0 | K98: 0 | L98: 0 | M98: 0 | N98: 0 | O98: 0 | P98: 0 | Q98: 0 | R98: 0 | S98: 0 | T98: 0 | U98: 0 | V98: 0 | W98: 0 | X98: 0
B99: Financial Markets Depth Index | C99: 0 | D99: 0 | E99: 0 | F99: 0 | G99: 0 | H99: 0 | I99: 0 | J99: 0 | K99: 0 | L99: 0 | M99: 0 | N99: 0 | O99: 0 | P99: 0 | Q99: 0 | R99: 0 | S99: 0 | T99: 0 | U99: 0 | V99: 0 | W99: 0 | X99: 0
B100: Financial Markets Efficiency Index | C100: 0 | D100: 0 | E100: 0 | F100: 0 | G100: 0 | H100: 0 | I100: 0 | J100: 0 | K100: 0 | L100: 0 | M100: 0 | N100: 0 | O100: 0 | P100: 0 | Q100: 0 | R100: 0 | S100: 0 | T100: 0 | U100: 0 | V100: 0 | W100: 0 | X100: 0
...

Sheet INST
A1: Country | B1: 2000 [YR2000] | C1: 2001 [YR2001] | D1: 2002 [YR2002] | E1: 2003 [YR2003] | F1: 2004 [YR2004] | G1: 2005 [YR2005] | H1: 2006 [YR2006] | I1: 2007 [YR2007] | J1: 2008 [YR2008] | K1: 2009 [YR2009] | L1: 2010 [YR2010] | M1: 2011 [YR2011] | N1: 2012 [YR2012] | O1: 2013 [YR2013] | P1: 2014 [YR2014] | Q1: 2015 [YR2015] | R1: 2016 [YR2016] | S1: 2017 [YR2017] | T1: 2018 [YR2018] | U1: 2019 [YR2019] | V1: 2020 [YR2020] | W1: 2021 [YR2021] | Z1: Average
A2: Angola | B2: 0.38 | C2: 0.36 | D2: 0.46 | E2: 0.48 | F2: 0.46 | G2: 0.46 | H2: 0.47 | I2: 0.48 | J2: 0.49 | K2: 0.49 | L2: 0.48 | M2: 0.46 | N2: 0.45 | O2: 0.46 | P2: 0.43 | Q2: 0.41 | R2: 0.42 | S2: 0.41 | T2: 0.45 | U2: 0.49 | V2: 0.47 | W2: 0.49 | Z2: =AVERAGE(B2:W2) -> 0.45227273
A3: Bangladesh | B3: 0.55 | C3: 0.5 | D3: 0.4 | E3: 0.4 | F3: 0.42 | G3: 0.47 | H3: 0.45 | I3: 0.47 | J3: 0.46 | K3: 0.52 | L3: 0.49 | M3: 0.47 | N3: 0.47 | O3: 0.47 | P3: 0.48 | Q3: 0.5 | R3: 0.49 | S3: 0.48 | T3: 0.48 | U3: 0.49 | V3: 0.49 | W3: 0.51 | Z3: =AVERAGE(B3:W3) -> 0.47545455
A4: Bolivia | B4: 0.6 | C4: 0.61 | D4: 0.56 | E4: 0.57 | F4: 0.52 | G4: 0.5 | H4: 0.48 | I4: 0.47 | J4: 0.51 | K4: 0.48 | L4: 0.47 | M4: 0.47 | N4: 0.45 | O4: 0.49 | P4: 0.52 | Q4: 0.51 | R4: 0.5 | S4: 0.51 | T4: 0.5 | U4: 0.49 | V4: 0.48 | W4: 0.47 | Z4: =AVERAGE(B4:W4) -> 0.50727273
A5: Cameroon | B5: 0.48 | C5: 0.45 | D5: 0.43 | E5: 0.42 | F5: 0.47 | G5: 0.49 | H5: 0.54 | I5: 0.55 | J5: 0.57 | K5: 0.55 | L5: 0.52 | M5: 0.48 | N5: 0.47 | O5: 0.47 | P5: 0.45 | Q5: 0.45 | R5: 0.45 | S5: 0.41 | T5: 0.42 | U5: 0.41 | V5: 0.42 | W5: 0.41 | Z5: =AVERAGE(B5:W5) -> 0.46863636
A6: Congo, Rep. | B6: 0.35 | C6: 0.42 | D6: 0.43 | E6: 0.42 | F6: 0.43 | G6: 0.43 | H6: 0.44 | I6: 0.44 | J6: 0.44 | K6: 0.43 | L6: 0.43 | M6: 0.43 | N6: 0.42 | O6: 0.42 | P6: 0.42 | Q6: 0.46 | R6: 0.43 | S6: 0.39 | T6: 0.4 | U6: 0.43 | V6: 0.41 | W6: 0.42 | Z6: =AVERAGE(B6:W6) -> 0.42227273
A7: Côte d'Ivoire | B7: 0.56 | C7: 0.34 | D7: 0.35 | E7: 0.37 | F7: 0.32 | G7: 0.29 | H7: 0.31 | I7: 0.33 | J7: 0.34 | K7: 0.34 | L7: 0.34 | M7: 0.37 | N7: 0.37 | O7: 0.37 | P7: 0.39 | Q7: 0.39 | R7: 0.41 | S7: 0.41 | T7: 0.41 | U7: 0.41 | V7: 0.39 | W7: 0.43 | Z7: =AVERAGE(B7:W7) -> 0.37454545
A8: Egypt, Arab Rep. | B8: 0.58 | C8: 0.59 | D8: 0.53 | E8: 0.54 | F8: 0.53 | G8: 0.54 | H8: 0.54 | I8: 0.52 | J8: 0.52 | K8: 0.51 | L8: 0.49 | M8: 0.45 | N8: 0.44 | O8: 0.44 | P8: 0.46 | Q8: 0.47 | R8: 0.47 | S8: 0.5 | T8: 0.5 | U8: 0.53 | V8: 0.51 | W8: 0.52 | Z8: =AVERAGE(B8:W8) -> 0.50818182
A9: Ghana | B9: 0.54 | C9: 0.5 | D9: 0.49 | E9: 0.49 | F9: 0.52 | G9: 0.55 | H9: 0.57 | I9: 0.56 | J9: 0.56 | K9: 0.56 | L9: 0.56 | M9: 0.58 | N9: 0.57 | O9: 0.57 | P9: 0.58 | Q9: 0.6 | R9: 0.59 | S9: 0.58 | T9: 0.59 | U9: 0.58 | V9: 0.59 | W9: 0.57 | Z9: =AVERAGE(B9:W9) -> 0.55909091
A10: Haiti | B10: 0.32 | C10: 0.34 | D10: 0.3 | E10: 0.29 | F10: 0.3 | G10: 0.25 | H10: 0.23 | I10: 0.29 | J10: 0.26 | K10: 0.27 | L10: 0.25 | M10: 0.27 | N10: 0.28 | O10: 0.27 | P10: 0.28 | Q10: 0.27 | R10: 0.28 | S10: 0.33 | T10: 0.32 | U10: 0.31 | V10: 0.3 | W10: 0.28 | Z10: =AVERAGE(B10:W10) -> 0.28590909
A11: Honduras | B11: 0.52 | C11: 0.53 | D11: 0.53 | E11: 0.53 | F11: 0.51 | G11: 0.51 | H11: 0.51 | I11: 0.5 | J11: 0.49 | K11: 0.49 | L11: 0.5 | M11: 0.51 | N11: 0.48 | O11: 0.49 | P11: 0.5 | Q11: 0.52 | R11: 0.52 | S11: 0.51 | T11: 0.54 | U11: 0.51 | V11: 0.53 | W11: 0.52 | Z11: =AVERAGE(B11:W11) -> 0.51136364
A12: India | B12: 0.62 | C12: 0.59 | D12: 0.62 | E12: 0.63 | F12: 0.67 | G12: 0.67 | H12: 0.66 | I12: 0.65 | J12: 0.65 | K12: 0.66 | L12: 0.65 | M12: 0.63 | N12: 0.63 | O12: 0.63 | P12: 0.64 | Q12: 0.67 | R12: 0.67 | S12: 0.67 | T12: 0.65 | U12: 0.67 | V12: 0.67 | W12: 0.68 | Z12: =AVERAGE(B12:W12) -> 0.64909091
A13: Jordan | B13: 0.71 | C13: 0.67 | D13: 0.66 | E13: 0.67 | F13: 0.68 | G13: 0.68 | H13: 0.69 | I13: 0.67 | J13: 0.66 | K13: 0.66 | L13: 0.65 | M13: 0.63 | N13: 0.59 | O13: 0.6 | P13: 0.61 | Q13: 0.61 | R13: 0.59 | S13: 0.57 | T13: 0.56 | U13: 0.57 | V13: 0.57 | W13: 0.55 | Z13: =AVERAGE(B13:W13) -> 0.62954545
... A28: Zambia | B28: 0.65 | C28: 0.6 | D28: 0.51 | E28: 0.52 | F28: 0.57 | G28: 0.59 | H28: 0.57 | I28: 0.58 | J28: 0.57 | K28: 0.57 | L28: 0.57 | M28: 0.56 | N28: 0.55 | O28: 0.55 | P28: 0.55 | Q28: 0.56 | R28: 0.57 | S28: 0.55 | T28: 0.54 | U28: 0.54 | V28: 0.53 | W28: 0.56 | Z28: =AVERAGE(B28:W28) -> 0.56181818
A32: 1
A33: 2
A34: 3
A35: 4
A36: 5
A37: 6

Sheet INST all indicators
A1: code | B1: country | C1: INST21 | D1: PRS21VA | E1: PRS21PV | F1: PRS21GE | G1: PRS21RQ | H1: PRS21RL | I1: PRS21CC | J1: INST20 | K1: PRS20VA | L1: PRS20PV | M1: PRS20GE | N1: PRS20RQ | O1: PRS20RL | P1: PRS20CC | Q1: INST19 | R1: PRS19VA | S1: PRS19PV | T1: PRS19GE | U1: PRS19RQ | V1: PRS19RL | W1: PRS19CC | X1: INST18 | Y1: PRS18VA | Z1: PRS18PV | AA1: PRS18GE | AB1: PRS18RQ | AC1: PRS18RL | AD1: PRS18CC | AE1: INST17 | AF1: PRS17VA | AG1: PRS17PV | AH1: PRS17GE | AI1: PRS17RQ | AJ1: PRS17RL | AK1: PRS17CC | AL1: INST16 | AM1: PRS16VA | AN1: PRS16PV | AO1: PRS16GE | AP1: PRS16RQ | AQ1: PRS16RL | AR1: PRS16CC | AS1: INST15 | AT1: PRS15VA | AU1: PRS15PV | AV1: PRS15GE | AW1: PRS15RQ | AX1: PRS15RL | AY1: PRS15CC | AZ1: INST14 | BA1: PRS14VA | BB1: PRS14PV | BC1: PRS14GE | BD1: PRS14RQ | BE1: PRS14RL | BF1: PRS14CC | BG1: INST13 | BH1: PRS13VA | BI1: PRS13PV | BJ1: PRS13GE | BK1: PRS13RQ | BL1: PRS13RL | BM1: PRS13CC | BN1: INST12 | BO1: PRS12VA | BP1: PRS12PV | BQ1: PRS12GE | BR1: PRS12RQ | BS1: PRS12RL | BT1: PRS12CC | BU1: INST11 | BV1: PRS11VA | BW1: PRS11PV | BX1: PRS11GE | BY1: PRS11RQ | BZ1: PRS11RL | CA1: PRS11CC | CB1: INST10 | CC1: PRS10VA | CD1: PRS10PV | CE1: PRS10GE | CF1: PRS10RQ | CG1: PRS10RL | CH1: PRS10CC | CI1: INST09 | CJ1: PRS09VA | CK1: PRS09PV | CL1: PRS09GE | CM1: PRS09RQ | CN1: PRS09RL | CO1: PRS09CC | CP1: INST08 | CQ1: PRS08VA | CR1: PRS08PV | CS1: PRS08GE | CT1: PRS08RQ | CU1: PRS08RL | CV1: PRS08CC | CW1: INST07 | CX1: PRS07VA | CY1: PRS07PV | CZ1: PRS07GE | DA1: PRS07RQ | DB1: PRS07RL | DC1: PRS07CC | DD1: INST06 | DE1: PRS06VA | DF1: PRS06PV | DG1: PRS06GE | DH1: PRS06RQ | DI1: PRS06RL | DJ1: PRS06CC | DK1: INST05 | DL1: PRS05VA | DM1: PRS05PV | DN1: PRS05GE | DO1: PRS05RQ | DP1: PRS05RL | DQ1: PRS05CC | DR1: INST04 | DS1: PRS04VA | DT1: PRS04PV | DU1: PRS04GE | DV1: PRS04RQ | DW1: PRS04RL | DX1: PRS04CC | DY1: INST03 | DZ1: PRS03VA | EA1: PRS03PV | EB1: PRS03GE | EC1: PRS03RQ | ED1: PRS03RL | EE1: PRS03CC | EF1: INST02 | EG1: PRS02VA | EH1: PRS02PV | EI1: PRS02GE | EJ1: PRS02RQ | EK1: PRS02RL | EL1: PRS02CC | EM1: INST01 | EN1: PRS01VA | EO1: PRS01PV | EP1: PRS01GE | EQ1: PRS01RQ | ER1: PRS01RL | ES1: PRS01CC | ET1: INST00 | EU1: PRS00VA | EV1: PRS00PV | EW1: PRS00GE | EX1: PRS00RQ | EY1: PRS00RL | EZ1: PRS00CC
A2: AGO | B2: Angola | C2: 0.49 | D2: 0.46 | E2: 0.66 | F2: 0.38 | G2: 0.68 | H2: 0.42 | I2: 0.33 | J2: 0.47 | K2: 0.46 | L2: 0.65 | M2: 0.38 | N2: 0.59 | O2: 0.42 | P2: 0.33 | Q2: 0.49 | R2: 0.38 | S2: 0.66 | T2: 0.38 | U2: 0.68 | V2: 0.42 | W2: 0.42 | X2: 0.45 | Y2: 0.38 | Z2: 0.67 | AA2: 0.38 | AB2: 0.64 | AC2: 0.42 | AD2: 0.25 | AE2: 0.41 | AF2: 0.38 | AG2: 0.65 | AH2: 0.38 | AI2: 0.45 | AJ2: 0.42 | AK2: 0.17 | AL2: 0.42 | AM2: 0.38 | AN2: 0.66 | AO2: 0.38 | AP2: 0.5 | AQ2: 0.42 | AR2: 0.17 | AS2: 0.41 | AT2: 0.38 | AU2: 0.65 | AV2: 0.38 | AW2: 0.5 | AX2: 0.42 | AY2: 0.17 | AZ2: 0.43 | BA2: 0.38 | BB2: 0.65 | BC2: 0.38 | BD2: 0.59 | BE2: 0.42 | BF2: 0.17 | BG2: 0.46 | BH2: 0.38 | BI2: 0.68 | BJ2: 0.38 | BK2: 0.64 | BL2: 0.42 | BM2: 0.25 | BN2: 0.45 | BO2: 0.38 | BP2: 0.69 | BQ2: 0.38 | BR2: 0.59 | BS2: 0.42 | BT2: 0.25 | BU2: 0.46 | BV2: 0.38 | BW2: 0.67 | BX2: 0.38 | BY2: 0.59 | BZ2: 0.42 | CA2: 0.33 | CB2: 0.48 | CC2: 0.33 | CD2: 0.73 | CE2: 0.38 | CF2: 0.64 | CG2: 0.5 | CH2: 0.33 | CI2: 0.49 | CJ2: 0.33 | CK2: 0.75 | CL2: 0.38 | CM2: 0.64 | CN2: 0.5 | CO2: 0.33 | CP2: 0.49 | CQ2: 0.33 | CR2: 0.75 | CS2: 0.38 | CT2: 0.64 | CU2: 0.5 | CV2: 0.33 | CW2: 0.48 | CX2: 0.33 | CY2: 0.73 | CZ2: 0.38 | DA2: 0.64 | DB2: 0.5 | DC2: 0.33 | DD2: 0.47 | DE2: 0.33 | DF2: 0.74 | DG2: 0.25 | DH2: 0.64 | DI2: 0.5 | DJ2: 0.33 | DK2: 0.46 | DL2: 0.33 | DM2: 0.73 | DN2: 0.25 | DO2: 0.59 | DP2: 0.5 | DQ2: 0.33 | DR2: 0.46 | DS2: 0.33 | DT2: 0.72 | DU2: 0.25 | DV2: 0.64 | DW2: 0.5 | DX2: 0.33 | DY2: 0.48 | DZ2: 0.42 | EA2: 0.74 | EB2: 0.25 | EC2: 0.64 | ED2: 0.5 | EE2: 0.33 | EF2: 0.46 | EG2: 0.33 | EH2: 0.67 | EI2: 0.25 | EJ2: 0.68 | EK2: 0.5 | EL2: 0.33 | EM2: 0.36 | EN2: 0.33 | EO2: 0.65 | EP2: 0.25 | EQ2: 0.09 | ER2: 0.5 | ES2: 0.33 | ET2: 0.38 | EU2: 0.42 | EV2: 0.51 | EW2: 0.25 | EX2: 0.27 | EY2: 0.5 | EZ2: 0.33
A3: BGD | B3: Bangladesh | C3: 0.51 | D3: 0.54 | E3: 0.57 | F3: 0.63 | G3: 0.55 | H3: 0.33 | I3: 0.42 | J3: 0.49 | K3: 0.54 | L3: 0.58 | M3: 0.5 | N3: 0.59 | O3: 0.33 | P3: 0.42 | Q3: 0.49 | R3: 0.54 | S3: 0.6 | T3: 0.5 | U3: 0.55 | V3: 0.33 | W3: 0.42 | X3: 0.48 | Y3: 0.54 | Z3: 0.55 | AA3: 0.5 | AB3: 0.55 | AC3: 0.33 | AD3: 0.42 | AE3: 0.48 | AF3: 0.54 | AG3: 0.56 | AH3: 0.5 | AI3: 0.55 | AJ3: 0.33 | AK3: 0.42 | AL3: 0.49 | AM3: 0.5 | AN3: 0.58 | AO3: 0.5 | AP3: 0.5 | AQ3: 0.33 | AR3: 0.5 | AS3: 0.5 | AT3: 0.5 | AU3: 0.58 | AV3: 0.5 | AW3: 0.59 | AX3: 0.33 | AY3: 0.5 | AZ3: 0.48 | BA3: 0.5 | BB3: 0.56 | BC3: 0.5 | BD3: 0.5 | BE3: 0.33 | BF3: 0.5 | BG3: 0.47 | BH3: 0.5 | BI3: 0.52 | BJ3: 0.5 | BK3: 0.45 | BL3: 0.33 | BM3: 0.5 | BN3: 0.47 | BO3: 0.5 | BP3: 0.55 | BQ3: 0.5 | BR3: 0.45 | BS3: 0.33 | BT3: 0.5 | BU3: 0.47 | BV3: 0.5 | BW3: 0.55 | BX3: 0.5 | BY3: 0.45 | BZ3: 0.33 | CA3: 0.5 | CB3: 0.49 | CC3: 0.5 | CD3: 0.58 | CE3: 0.5 | CF3: 0.55 | CG3: 0.33 | CH3: 0.5 | CI3: 0.52 | CJ3: 0.54 | CK3: 0.62 | CL3: 0.5 | CM3: 0.55 | CN3: 0.42 | CO3: 0.5 | CP3: 0.46 | CQ3: 0.33 | CR3: 0.57 | CS3: 0.5 | CT3: 0.55 | CU3: 0.42 | CV3: 0.42 | CW3: 0.47 | CX3: 0.38 | CY3: 0.55 | CZ3: 0.5 | DA3: 0.55 | DB3: 0.42 | DC3: 0.42 | DD3: 0.45 | DE3: 0.46 | DF3: 0.56 | DG3: 0.5 | DH3: 0.5 | DI3: 0.42 | DJ3: 0.25 | DK3: 0.47 | DL3: 0.5 | DM3: 0.59 | DN3: 0.5 | DO3: 0.55 | DP3: 0.42 | DQ3: 0.25 | DR3: 0.42 | DS3: 0.46 | DT3: 0.58 | DU3: 0.5 | DV3: 0.5 | DW3: 0.25 | DX3: 0.25 | DY3: 0.4 | DZ3: 0.42 | EA3: 0.63 | EB3: 0.5 | EC3: 0.5 | ED3: 0.17 | EE3: 0.17 | EF3: 0.4 | EG3: 0.46 | EH3: 0.68 | EI3: 0.5 | EJ3: 0.36 | EK3: 0.25 | EL3: 0.17 | EM3: 0.5 | EN3: 0.67 | EO3: 0.73 | EP3: 0.5 | EQ3: 0.45 | ER3: 0.33 | ES3: 0.33 | ET3: 0.55 | EU3: 0.67 | EV3: 0.82 | EW3: 0.5 | EX3: 0.45 | EY3: 0.5 | EZ3: 0.33
A4: BOL | B4: Bolivia | C4: 0.47 | D4: 0.46 | E4: 0.63 | F4: 0.63 | G4: 0.5 | H4: 0.33 | I4: 0.25 | J4: 0.48 | K4: 0.46 | L4: 0.66 | M4: 0.63 | N4: 0.5 | O4: 0.33 | P4: 0.33 | Q4: 0.49 | R4: 0.46 | S4: 0.6 | T4: 0.63 | U4: 0.5 | V4: 0.42 | W4: 0.33 | X4: 0.5 | Y4: 0.54 | Z4: 0.59 | AA4: 0.63 | AB4: 0.5 | AC4: 0.42 | AD4: 0.33 | AE4: 0.51 | AF4: 0.54 | AG4: 0.61 | AH4: 0.63 | AI4: 0.5 | AJ4: 0.42 | AK4: 0.33 | AL4: 0.5 | AM4: 0.54 | AN4: 0.61 | AO4: 0.63 | AP4: 0.45 | AQ4: 0.42 | AR4: 0.33 | AS4: 0.51 | AT4: 0.54 | AU4: 0.65 | AV4: 0.63 | AW4: 0.5 | AX4: 0.42 | AY4: 0.33 | AZ4: 0.52 | BA4: 0.54 | BB4: 0.7 | BC4: 0.63 | BD4: 0.5 | BE4: 0.42 | BF4: 0.33 | BG4: 0.49 | BH4: 0.54 | BI4: 0.65 | BJ4: 0.63 | BK4: 0.36 | BL4: 0.42 | BM4: 0.33 | BN4: 0.45 | BO4: 0.54 | BP4: 0.64 | BQ4: 0.5 | BR4: 0.36 | BS4: 0.42 | BT4: 0.25 | BU4: 0.47 | BV4: 0.54 | BW4: 0.64 | BX4: 0.5 | BY4: 0.36 | BZ4: 0.42 | CA4: 0.33 | CB4: 0.47 | CC4: 0.54 | CD4: 0.68 | CE4: 0.5 | CF4: 0.36 | CG4: 0.42 | CH4: 0.33 | CI4: 0.48 | CJ4: 0.58 | CK4: 0.7 | CL4: 0.5 | CM4: 0.36 | CN4: 0.42 | CO4: 0.33 | CP4: 0.51 | CQ4: 0.67 | CR4: 0.68 | CS4: 0.5 | CT4: 0.36 | CU4: 0.5 | CV4: 0.33 | CW4: 0.47 | CX4: 0.67 | CY4: 0.66 | CZ4: 0.5 | DA4: 0.18 | DB4: 0.5 | DC4: 0.33 | DD4: 0.48 | DE4: 0.75 | DF4: 0.6 | DG4: 0.5 | DH4: 0.18 | DI4: 0.5 | DJ4: 0.33 | DK4: 0.5 | DL4: 0.58 | DM4: 0.56 | DN4: 0.5 | DO4: 0.5 | DP4: 0.5 | DQ4: 0.33 | DR4: 0.52 | DS4: 0.58 | DT4: 0.61 | DU4: 0.5 | DV4: 0.59 | DW4: 0.5 | DX4: 0.33 | DY4: 0.57 | DZ4: 0.58 | EA4: 0.7 | EB4: 0.5 | EC4: 0.77 | ED4: 0.5 | EE4: 0.33 | EF4: 0.56 | EG4: 0.58 | EH4: 0.67 | EI4: 0.5 | EJ4: 0.77 | EK4: 0.5 | EL4: 0.33 | EM4: 0.61 | EN4: 0.58 | EO4: 0.76 | EP4: 0.5 | EQ4: 0.82 | ER4: 0.5 | ES4: 0.5 | ET4: 0.6 | EU4: 0.58 | EV4: 0.67 | EW4: 0.5 | EX4: 0.82 | EY4: 0.5 | EZ4: 0.5
A5: CMR | B5: Cameroon | C5: 0.41 | D5: 0.38 | E5: 0.56 | F5: 0.38 | G5: 0.55 | H5: 0.33 | I5: 0.25 | J5: 0.42 | K5: 0.38 | L5: 0.55 | M5: 0.38 | N5: 0.64 | O5: 0.33 | P5: 0.25 | Q5: 0.41 | R5: 0.38 | S5: 0.57 | T5: 0.38 | U5: 0.55 | V5: 0.33 | W5: 0.25 | X5: 0.42 | Y5: 0.42 | Z5: 0.58 | AA5: 0.38 | AB5: 0.55 | AC5: 0.33 | AD5: 0.25 | AE5: 0.41 | AF5: 0.42 | AG5: 0.57 | AH5: 0.38 | AI5: 0.55 | AJ5: 0.33 | AK5: 0.25 | AL5: 0.45 | AM5: 0.42 | AN5: 0.61 | AO5: 0.38 | AP5: 0.64 | AQ5: 0.33 | AR5: 0.33 | AS5: 0.45 | AT5: 0.42 | AU5: 0.63 | AV5: 0.38 | AW5: 0.64 | AX5: 0.33 | AY5: 0.33 | AZ5: 0.45 | BA5: 0.42 | BB5: 0.63 | BC5: 0.38 | BD5: 0.64 | BE5: 0.33 | BF5: 0.33 | BG5: 0.47 | BH5: 0.42 | BI5: 0.71 | BJ5: 0.38 | BK5: 0.64 | BL5: 0.33 | BM5: 0.33 | BN5: 0.47 | BO5: 0.46 | BP5: 0.7 | BQ5: 0.38 | BR5: 0.59 | BS5: 0.33 | BT5: 0.33 | BU5: 0.48 | BV5: 0.46 | BW5: 0.71 | BX5: 0.38 | BY5: 0.59 | BZ5: 0.33 | CA5: 0.42 | CB5: 0.52 | CC5: 0.5 | CD5: 0.75 | CE5: 0.38 | CF5: 0.73 | CG5: 0.33 | CH5: 0.42 | CI5: 0.55 | CJ5: 0.5 | CK5: 0.79 | CL5: 0.38 | CM5: 0.73 | CN5: 0.33 | CO5: 0.58 | CP5: 0.57 | CQ5: 0.54 | CR5: 0.79 | CS5: 0.38 | CT5: 0.73 | CU5: 0.33 | CV5: 0.67 | CW5: 0.55 | CX5: 0.63 | CY5: 0.79 | CZ5: 0.25 | DA5: 0.73 | DB5: 0.33 | DC5: 0.58 | DD5: 0.54 | DE5: 0.63 | DF5: 0.78 | DG5: 0.25 | DH5: 0.68 | DI5: 0.42 | DJ5: 0.5 | DK5: 0.49 | DL5: 0.63 | DM5: 0.79 | DN5: 0.25 | DO5: 0.64 | DP5: 0.33 | DQ5: 0.33 | DR5: 0.47 | DS5: 0.63 | DT5: 0.64 | DU5: 0.25 | DV5: 0.64 | DW5: 0.33 | DX5: 0.33 | DY5: 0.42 | DZ5: 0.5 | EA5: 0.63 | EB5: 0.25 | EC5: 0.5 | ED5: 0.33 | EE5: 0.33 | EF5: 0.43 | EG5: 0.5 | EH5: 0.65 | EI5: 0.25 | EJ5: 0.5 | EK5: 0.33 | EL5: 0.33 | EM5: 0.45 | EN5: 0.5 | EO5: 0.63 | EP5: 0.25 | EQ5: 0.64 | ER5: 0.33 | ES5: 0.33 | ET5: 0.48 | EU5: 0.5 | EV5: 0.65 | EW5: 0.25 | EX5: 0.64 | EY5: 0.5 | EZ5: 0.33
A6: COG | B6: Congo, Rep. | C6: 0.42 | D6: 0.46 | E6: 0.75 | F6: 0.25 | G6: 0.59 | H6: 0.33 | I6: 0.17 | J6: 0.41 | K6: 0.46 | L6: 0.73 | M6: 0.25 | N6: 0.5 | O6: 0.33 | P6: 0.17 | Q6: 0.43 | R6: 0.46 | S6: 0.72 | T6: 0.25 | U6: 0.64 | V6: 0.33 | W6: 0.17 | X6: 0.4 | Y6: 0.46 | Z6: 0.71 | AA6: 0.25 | AB6: 0.5 | AC6: 0.33 | AD6: 0.17 | AE6: 0.39 | AF6: 0.46 | AG6: 0.7 | AH6: 0.25 | AI6: 0.45 | AJ6: 0.33 | AK6: 0.17 | AL6: 0.43 | AM6: 0.5 | AN6: 0.7 | AO6: 0.25 | AP6: 0.55 | AQ6: 0.33 | AR6: 0.25 | AS6: 0.46 | AT6: 0.5 | AU6: 0.73 | AV6: 0.25 | AW6: 0.68 | AX6: 0.33 | AY6: 0.25 | AZ6: 0.42 | BA6: 0.25 | BB6: 0.73 | BC6: 0.25 | BD6: 0.68 | BE6: 0.33 | BF6: 0.25 | BG6: 0.42 | BH6: 0.25 | BI6: 0.73 | BJ6: 0.25 | BK6: 0.68 | BL6: 0.33 | BM6: 0.25 | BN6: 0.42 | BO6: 0.25 | BP6: 0.73 | BQ6: 0.25 | BR6: 0.68 | BS6: 0.33 | BT6: 0.25 | BU6: 0.43 | BV6: 0.25 | BW6: 0.72 | BX6: 0.25 | BY6: 0.68 | BZ6: 0.33 | CA6: 0.33 | CB6: 0.43 | CC6: 0.25 | CD6: 0.76 | CE6: 0.25 | CF6: 0.68 | CG6: 0.33 | CH6: 0.33 | CI6: 0.43 | CJ6: 0.25 | CK6: 0.76 | CL6: 0.25 | CM6: 0.68 | CN6: 0.33 | CO6: 0.33 | CP6: 0.44 | CQ6: 0.25 | CR6: 0.76 | CS6: 0.25 | CT6: 0.73 | CU6: 0.33 | CV6: 0.33 | CW6: 0.44 | CX6: 0.25 | CY6: 0.73 | CZ6: 0.25 | DA6: 0.73 | DB6: 0.33 | DC6: 0.33 | DD6: 0.44 | DE6: 0.25 | DF6: 0.76 | DG6: 0.25 | DH6: 0.73 | DI6: 0.33 | DJ6: 0.33 | DK6: 0.43 | DL6: 0.25 | DM6: 0.76 | DN6: 0.25 | DO6: 0.68 | DP6: 0.33 | DQ6: 0.33 | DR6: 0.43 | DS6: 0.25 | DT6: 0.8 | DU6: 0.25 | DV6: 0.59 | DW6: 0.33 | DX6: 0.33 | DY6: 0.42 | DZ6: 0.25 | EA6: 0.79 | EB6: 0.25 | EC6: 0.59 | ED6: 0.33 | EE6: 0.33 | EF6: 0.43 | EG6: 0.25 | EH6: 0.76 | EI6: 0.25 | EJ6: 0.68 | EK6: 0.33 | EL6: 0.33 | EM6: 0.42 | EN6: 0.08 | EO6: 0.76 | EP6: 0.25 | EQ6: 0.45 | ER6: 0.33 | ES6: 0.67 | ET6: 0.35 | EU6: 0.08 | EV6: 0.67 | EW6: 0.25 | EX6: 0.27 | EY6: 0.17 | EZ6: 0.67
A7: CIV | B7: Côte d'Ivoire | C7: 0.43 | D7: 0.54 | E7: 0.62 | F7: 0 | G7: 0.59 | H7: 0.42 | I7: 0.42 | J7: 0.39 | K7: 0.5 | L7: 0.57 | M7: 0 | N7: 0.55 | O7: 0.42 | P7: 0.33 | Q7: 0.41 | R7: 0.54 | S7: 0.55 | T7: 0 | U7: 0.64 | V7: 0.42 | W7: 0.33 | X7: 0.41 | Y7: 0.58 | Z7: 0.54 | AA7: 0 | AB7: 0.59 | AC7: 0.42 | AD7: 0.33 | AE7: 0.41 | AF7: 0.54 | AG7: 0.56 | AH7: 0 | AI7: 0.59 | AJ7: 0.42 | AK7: 0.33 | AL7: 0.41 | AM7: 0.5 | AN7: 0.57 | AO7: 0 | AP7: 0.64 | AQ7: 0.42 | AR7: 0.33 | AS7: 0.39 | AT7: 0.38 | AU7: 0.59 | AV7: 0 | AW7: 0.64 | AX7: 0.42 | AY7: 0.33 | AZ7: 0.39 | BA7: 0.38 | BB7: 0.59 | BC7: 0 | BD7: 0.64 | BE7: 0.42 | BF7: 0.33 | BG7: 0.37 | BH7: 0.38 | BI7: 0.56 | BJ7: 0 | BK7: 0.59 | BL7: 0.42 | BM7: 0.25 | BN7: 0.37 | BO7: 0.38 | BP7: 0.52 | BQ7: 0 | BR7: 0.64 | BS7: 0.42 | BT7: 0.25 | BU7: 0.37 | BV7: 0.38 | BW7: 0.59 | BX7: 0 | BY7: 0.5 | BZ7: 0.42 | CA7: 0.33 | CB7: 0.34 | CC7: 0.38 | CD7: 0.54 | CE7: 0 | CF7: 0.36 | CG7: 0.42 | CH7: 0.33 | CI7: 0.34 | CJ7: 0.29 | CK7: 0.55 | CL7: 0 | CM7: 0.36 | CN7: 0.42 | CO7: 0.42 | CP7: 0.34 | CQ7: 0.29 | CR7: 0.57 | CS7: 0 | CT7: 0.36 | CU7: 0.42 | CV7: 0.42 | CW7: 0.33 | CX7: 0.29 | CY7: 0.58 | CZ7: 0 | DA7: 0.36 | DB7: 0.42 | DC7: 0.33 | DD7: 0.31 | DE7: 0.29 | DF7: 0.56 | DG7: 0 | DH7: 0.36 | DI7: 0.42 | DJ7: 0.25 | DK7: 0.29 | DL7: 0.25 | DM7: 0.47 | DN7: 0 | DO7: 0.36 | DP7: 0.42 | DQ7: 0.25 | DR7: 0.32 | DS7: 0.25 | DT7: 0.53 | DU7: 0 | DV7: 0.41 | DW7: 0.42 | DX7: 0.33 | DY7: 0.37 | DZ7: 0.25 | EA7: 0.59 | EB7: 0 | EC7: 0.45 | ED7: 0.42 | EE7: 0.5 | EF7: 0.35 | EG7: 0.21 | EH7: 0.49 | EI7: 0 | EJ7: 0.45 | EK7: 0.42 | EL7: 0.5 | EM7: 0.34 | EN7: 0.33 | EO7: 0.61 | EP7: 0 | EQ7: 0.09 | ER7: 0.5 | ES7: 0.5 | ET7: 0.56 | EU7: 0.58 | EV7: 0.69 | EW7: 0.5 | EX7: 0.73 | EY7: 0.5 | EZ7: 0.33
A8: EGY | B8: Egypt, Arab Rep. | C8: 0.52 | D8: 0.25 | E8: 0.7 | F8: 0.63 | G8: 0.73 | H8: 0.5 | I8: 0.33 | J8: 0.51 | K8: 0.25 | L8: 0.7 | M8: 0.63 | N8: 0.68 | O8: 0.5 | P8: 0.33 | Q8: 0.53 | R8: 0.29 | S8: 0.74 | T8: 0.63 | U8: 0.68 | V8: 0.5 | W8: 0.33 | X8: 0.5 | Y8: 0.29 | Z8: 0.73 | AA8: 0.5 | AB8: 0.64 | AC8: 0.5 | AD8: 0.33 | AE8: 0.5 | AF8: 0.33 | AG8: 0.71 | AH8: 0.5 | AI8: 0.64 | AJ8: 0.5 | AK8: 0.33 | AL8: 0.47 | AM8: 0.25 | AN8: 0.66 | AO8: 0.5 | AP8: 0.59 | AQ8: 0.5 | AR8: 0.33 | AS8: 0.47 | AT8: 0.25 | AU8: 0.66 | AV8: 0.5 | AW8: 0.55 | AX8: 0.5 | AY8: 0.33 | AZ8: 0.46 | BA8: 0.25 | BB8: 0.65 | BC8: 0.5 | BD8: 0.5 | BE8: 0.5 | BF8: 0.33 | BG8: 0.44 | BH8: 0.25 | BI8: 0.59 | BJ8: 0.5 | BK8: 0.45 | BL8: 0.5 | BM8: 0.33 | BN8: 0.44 | BO8: 0.21 | BP8: 0.63 | BQ8: 0.5 | BR8: 0.45 | BS8: 0.5 | BT8: 0.33 | BU8: 0.45 | BV8: 0.25 | BW8: 0.64 | BX8: 0.5 | BY8: 0.45 | BZ8: 0.5 | CA8: 0.33 | CB8: 0.49 | CC8: 0.33 | CD8: 0.72 | CE8: 0.5 | CF8: 0.5 | CG8: 0.58 | CH8: 0.33 | CI8: 0.51 | CJ8: 0.42 | CK8: 0.75 | CL8: 0.5 | CM8: 0.5 | CN8: 0.58 | CO8: 0.33 | CP8: 0.52 | CQ8: 0.42 | CR8: 0.77 | CS8: 0.5 | CT8: 0.5 | CU8: 0.58 | CV8: 0.33 | CW8: 0.52 | CX8: 0.42 | CY8: 0.79 | CZ8: 0.5 | DA8: 0.5 | DB8: 0.58 | DC8: 0.33 | DD8: 0.54 | DE8: 0.42 | DF8: 0.84 | DG8: 0.5 | DH8: 0.5 | DI8: 0.67 | DJ8: 0.33 | DK8: 0.54 | DL8: 0.46 | DM8: 0.84 | DN8: 0.5 | DO8: 0.5 | DP8: 0.67 | DQ8: 0.25 | DR8: 0.53 | DS8: 0.42 | DT8: 0.86 | DU8: 0.5 | DV8: 0.5 | DW8: 0.67 | DX8: 0.25 | DY8: 0.54 | DZ8: 0.42 | EA8: 0.89 | EB8: 0.5 | EC8: 0.5 | ED8: 0.67 | EE8: 0.25 | EF8: 0.53 | EG8: 0.42 | EH8: 0.86 | EI8: 0.5 | EJ8: 0.5 | EK8: 0.67 | EL8: 0.25 | EM8: 0.59 | EN8: 0.42 | EO8: 0.8 | EP8: 0.5 | EQ8: 0.82 | ER8: 0.67 | ES8: 0.33 | ET8: 0.58 | EU8: 0.42 | EV8: 0.82 | EW8: 0.5 | EX8: 0.73 | EY8: 0.67 | EZ8: 0.33
A9: GHA | B9: Ghana | C9: 0.57 | D9: 0.67 | E9: 0.68 | F9: 0.63 | G9: 0.55 | H9: 0.42 | I9: 0.5 | J9: 0.59 | K9: 0.67 | L9: 0.7 | M9: 0.63 | N9: 0.64 | O9: 0.42 | P9: 0.5 | Q9: 0.58 | R9: 0.67 | S9: 0.68 | T9: 0.63 | U9: 0.59 | V9: 0.42 | W9: 0.5 | X9: 0.59 | Y9: 0.67 | Z9: 0.69 | AA9: 0.63 | AB9: 0.64 | AC9: 0.42 | AD9: 0.5 | AE9: 0.58 | AF9: 0.67 | AG9: 0.69 | AH9: 0.63 | AI9: 0.64 | AJ9: 0.42 | AK9: 0.42 | AL9: 0.59 | AM9: 0.67 | AN9: 0.7 | AO9: 0.63 | AP9: 0.64 | AQ9: 0.42 | AR9: 0.5 | AS9: 0.6 | AT9: 0.67 | AU9: 0.68 | AV9: 0.63 | AW9: 0.68 | AX9: 0.42 | AY9: 0.5 | AZ9: 0.58 | BA9: 0.67 | BB9: 0.67 | BC9: 0.63 | BD9: 0.59 | BE9: 0.42 | BF9: 0.5 | BG9: 0.57 | BH9: 0.67 | BI9: 0.71 | BJ9: 0.63 | BK9: 0.59 | BL9: 0.42 | BM9: 0.42 | BN9: 0.57 | BO9: 0.67 | BP9: 0.73 | BQ9: 0.63 | BR9: 0.59 | BS9: 0.42 | BT9: 0.42 | BU9: 0.58 | BV9: 0.67 | BW9: 0.74 | BX9: 0.63 | BY9: 0.59 | BZ9: 0.42 | CA9: 0.42 | CB9: 0.56 | CC9: 0.67 | CD9: 0.69 | CE9: 0.63 | CF9: 0.55 | CG9: 0.42 | CH9: 0.42 | CI9: 0.56 | CJ9: 0.67 | CK9: 0.74 | CL9: 0.63 | CM9: 0.64 | CN9: 0.42 | CO9: 0.25 | CP9: 0.56 | CQ9: 0.67 | CR9: 0.74 | CS9: 0.63 | CT9: 0.68 | CU9: 0.42 | CV9: 0.25 | CW9: 0.56 | CX9: 0.67 | CY9: 0.75 | CZ9: 0.63 | DA9: 0.68 | DB9: 0.42 | DC9: 0.25 | DD9: 0.57 | DE9: 0.67 | DF9: 0.77 | DG9: 0.63 | DH9: 0.68 | DI9: 0.42 | DJ9: 0.25 | DK9: 0.55 | DL9: 0.67 | DM9: 0.77 | DN9: 0.5 | DO9: 0.68 | DP9: 0.42 | DQ9: 0.25 | DR9: 0.52 | DS9: 0.58 | DT9: 0.68 | DU9: 0.5 | DV9: 0.59 | DW9: 0.33 | DX9: 0.42 | DY9: 0.49 | DZ9: 0.46 | EA9: 0.68 | EB9: 0.5 | EC9: 0.55 | ED9: 0.33 | EE9: 0.42 | EF9: 0.49 | EG9: 0.46 | EH9: 0.69 | EI9: 0.5 | EJ9: 0.55 | EK9: 0.33 | EL9: 0.42 | EM9: 0.5 | EN9: 0.42 | EO9: 0.67 | EP9: 0.5 | EQ9: 0.73 | ER9: 0.33 | ES9: 0.33 | ET9: 0.54 | EU9: 0.42 | EV9: 0.74 | EW9: 0.5 | EX9: 0.73 | EY9: 0.5 | EZ9: 0.33
A10: HTI | B10: Haiti | C10: 0.28 | D10: 0.25 | E10: 0.66 | F10: 0 | G10: 0.36 | H10: 0.25 | I10: 0.17 | J10: 0.3 | K10: 0.29 | L10: 0.66 | M10: 0 | N10: 0.36 | O10: 0.25 | P10: 0.25 | Q10: 0.31 | R10: 0.33 | S10: 0.67 | T10: 0 | U10: 0.36 | V10: 0.25 | W10: 0.25 | X10: 0.32 | Y10: 0.38 | Z10: 0.7 | AA10: 0 | AB10: 0.36 | AC10: 0.25 | AD10: 0.25 | AE10: 0.33 | AF10: 0.38 | AG10: 0.72 | AH10: 0 | AI10: 0.36 | AJ10: 0.25 | AK10: 0.25 | AL10: 0.28 | AM10: 0.29 | AN10: 0.67 | AO10: 0 | AP10: 0.27 | AQ10: 0.25 | AR10: 0.17 | AS10: 0.27 | AT10: 0.29 | AU10: 0.65 | AV10: 0 | AW10: 0.27 | AX10: 0.25 | AY10: 0.17 | AZ10: 0.28 | BA10: 0.29 | BB10: 0.69 | BC10: 0 | BD10: 0.27 | BE10: 0.25 | BF10: 0.17 | BG10: 0.27 | BH10: 0.25 | BI10: 0.7 | BJ10: 0 | BK10: 0.27 | BL10: 0.25 | BM10: 0.17 | BN10: 0.28 | BO10: 0.29 | BP10: 0.72 | BQ10: 0 | BR10: 0.27 | BS10: 0.25 | BT10: 0.17 | BU10: 0.27 | BV10: 0.21 | BW10: 0.73 | BX10: 0 | BY10: 0.27 | BZ10: 0.25 | CA10: 0.17 | CB10: 0.25 | CC10: 0.21 | CD10: 0.62 | CE10: 0 | CF10: 0.27 | CG10: 0.25 | CH10: 0.17 | CI10: 0.27 | CJ10: 0.21 | CK10: 0.66 | CL10: 0 | CM10: 0.32 | CN10: 0.25 | CO10: 0.17 | CP10: 0.26 | CQ10: 0.21 | CR10: 0.64 | CS10: 0 | CT10: 0.32 | CU10: 0.25 | CV10: 0.17 | CW10: 0.29 | CX10: 0.21 | CY10: 0.72 | CZ10: 0 | DA10: 0.32 | DB10: 0.33 | DC10: 0.17 | DD10: 0.23 | DE10: 0 | DF10: 0.64 | DG10: 0 | DH10: 0.32 | DI10: 0.25 | DJ10: 0.17 | DK10: 0.25 | DL10: 0 | DM10: 0.57 | DN10: 0 | DO10: 0.32 | DP10: 0.33 | DQ10: 0.25 | DR10: 0.3 | DS10: 0 | DT10: 0.58 | DU10: 0 | DV10: 0.41 | DW10: 0.42 | DX10: 0.42 | DY10: 0.29 | DZ10: 0.29 | EA10: 0.59 | EB10: 0 | EC10: 0.36 | ED10: 0.33 | EE10: 0.17 | EF10: 0.3 | EG10: 0.29 | EH10: 0.62 | EI10: 0 | EJ10: 0.36 | EK10: 0.33 | EL10: 0.17 | EM10: 0.34 | EN10: 0.42 | EO10: 0.67 | EP10: 0 | EQ10: 0.27 | ER10: 0.33 | ES10: 0.33 | ET10: 0.32 | EU10: 0.42 | EV10: 0.55 | EW10: 0 | EX10: 0.27 | EY10: 0.33 | EZ10: 0.33
A11: HND | B11: Honduras | C11: 0.52 | D11: 0.58 | E11: 0.75 | F11: 0.5 | G11: 0.64 | H11: 0.42 | I11: 0.25 | J11: 0.53 | K11: 0.54 | L11: 0.73 | M11: 0.5 | N11: 0.64 | O11: 0.42 | P11: 0.33 | Q11: 0.51 | R11: 0.58 | S11: 0.73 | T11: 0.5 | U11: 0.59 | V11: 0.33 | W11: 0.33 | X11: 0.54 | Y11: 0.58 | Z11: 0.75 | AA11: 0.5 | AB11: 0.64 | AC11: 0.33 | AD11: 0.42 | AE11: 0.51 | AF11: 0.58 | AG11: 0.73 | AH11: 0.5 | AI11: 0.59 | AJ11: 0.33 | AK11: 0.33 | AL11: 0.52 | AM11: 0.58 | AN11: 0.75 | AO11: 0.5 | AP11: 0.59 | AQ11: 0.25 | AR11: 0.42 | AS11: 0.52 | AT11: 0.58 | AU11: 0.78 | AV11: 0.5 | AW11: 0.59 | AX11: 0.25 | AY11: 0.42 | AZ11: 0.5 | BA11: 0.63 | BB11: 0.77 | BC11: 0.5 | BD11: 0.55 | BE11: 0.25 | BF11: 0.33 | BG11: 0.49 | BH11: 0.67 | BI11: 0.75 | BJ11: 0.5 | BK11: 0.55 | BL11: 0.25 | BM11: 0.25 | BN11: 0.48 | BO11: 0.63 | BP11: 0.78 | BQ11: 0.5 | BR11: 0.5 | BS11: 0.25 | BT11: 0.25 | BU11: 0.51 | BV11: 0.63 | BW11: 0.79 | BX11: 0.5 | BY11: 0.5 | BZ11: 0.33 | CA11: 0.33 | CB11: 0.5 | CC11: 0.63 | CD11: 0.77 | CE11: 0.5 | CF11: 0.5 | CG11: 0.25 | CH11: 0.33 | CI11: 0.49 | CJ11: 0.58 | CK11: 0.78 | CL11: 0.5 | CM11: 0.5 | CN11: 0.25 | CO11: 0.33 | CP11: 0.49 | CQ11: 0.63 | CR11: 0.74 | CS11: 0.5 | CT11: 0.5 | CU11: 0.25 | CV11: 0.33 | CW11: 0.5 | CX11: 0.67 | CY11: 0.77 | CZ11: 0.5 | DA11: 0.5 | DB11: 0.25 | DC11: 0.33 | DD11: 0.51 | DE11: 0.67 | DF11: 0.78 | DG11: 0.5 | DH11: 0.55 | DI11: 0.25 | DJ11: 0.33 | DK11: 0.51 | DL11: 0.67 | DM11: 0.73 | DN11: 0.5 | DO11: 0.59 | DP11: 0.25 | DQ11: 0.33 | DR11: 0.51 | DS11: 0.58 | DT11: 0.78 | DU11: 0.5 | DV11: 0.59 | DW11: 0.25 | DX11: 0.33 | DY11: 0.53 | DZ11: 0.58 | EA11: 0.8 | EB11: 0.5 | EC11: 0.64 | ED11: 0.25 | EE11: 0.42 | EF11: 0.53 | EG11: 0.58 | EH11: 0.79 | EI11: 0.5 | EJ11: 0.64 | EK11: 0.25 | EL11: 0.42 | EM11: 0.53 | EN11: 0.58 | EO11: 0.82 | EP11: 0.5 | EQ11: 0.64 | ER11: 0.33 | ES11: 0.33 | ET11: 0.52 | EU11: 0.5 | EV11: 0.84 | EW11: 0.5 | EX11: 0.64 | EY11: 0.33 | EZ11: 0.33
A12: IND | B12: India | C12: 0.68 | D12: 0.83 | E12: 0.63 | F12: 0.75 | G12: 0.73 | H12: 0.75 | I12: 0.42 | J12: 0.67 | K12: 0.83 | L12: 0.57 | M12: 0.75 | N12: 0.73 | O12: 0.75 | P12: 0.42 | Q12: 0.67 | R12: 0.83 | S12: 0.56 | T12: 0.75 | U12: 0.73 | V12: 0.75 | W12: 0.42 | X12: 0.65 | Y12: 0.83 | Z12: 0.54 | AA12: 0.75 | AB12: 0.64 | AC12: 0.75 | AD12: 0.42 | AE12: 0.67 | AF12: 0.83 | AG12: 0.56 | AH12: 0.75 | AI12: 0.68 | AJ12: 0.75 | AK12: 0.42 | AL12: 0.67 | AM12: 0.83 | AN12: 0.58 | AO12: 0.75 | AP12: 0.68 | AQ12: 0.75 | AR12: 0.42 | AS12: 0.67 | AT12: 0.83 | AU12: 0.56 | AV12: 0.75 | AW12: 0.68 | AX12: 0.75 | AY12: 0.42 | AZ12: 0.64 | BA12: 0.83 | BB12: 0.58 | BC12: 0.75 | BD12: 0.59 | BE12: 0.67 | BF12: 0.42 | BG12: 0.63 | BH12: 0.83 | BI12: 0.52 | BJ12: 0.75 | BK12: 0.59 | BL12: 0.67 | BM12: 0.42 | BN12: 0.63 | BO12: 0.83 | BP12: 0.54 | BQ12: 0.75 | BR12: 0.59 | BS12: 0.67 | BT12: 0.42 | BU12: 0.63 | BV12: 0.83 | BW12: 0.52 | BX12: 0.75 | BY12: 0.68 | BZ12: 0.67 | CA12: 0.33 | CB12: 0.65 | CC12: 0.83 | CD12: 0.55 | CE12: 0.75 | CF12: 0.68 | CG12: 0.67 | CH12: 0.42 | CI12: 0.66 | CJ12: 0.83 | CK12: 0.62 | CL12: 0.75 | CM12: 0.68 | CN12: 0.67 | CO12: 0.42 | CP12: 0.65 | CQ12: 0.83 | CR12: 0.57 | CS12: 0.75 | CT12: 0.68 | CU12: 0.67 | CV12: 0.42 | CW12: 0.65 | CX12: 0.83 | CY12: 0.56 | CZ12: 0.75 | DA12: 0.68 | DB12: 0.67 | DC12: 0.42 | DD12: 0.66 | DE12: 0.83 | DF12: 0.6 | DG12: 0.75 | DH12: 0.68 | DI12: 0.67 | DJ12: 0.42 | DK12: 0.67 | DL12: 0.83 | DM12: 0.6 | DN12: 0.75 | DO12: 0.77 | DP12: 0.67 | DQ12: 0.42 | DR12: 0.67 | DS12: 0.83 | DT12: 0.64 | DU12: 0.75 | DV12: 0.73 | DW12: 0.67 | DX12: 0.42 | DY12: 0.63 | DZ12: 0.83 | EA12: 0.61 | EB12: 0.75 | EC12: 0.68 | ED12: 0.67 | EE12: 0.25 | EF12: 0.62 | EG12: 0.83 | EH12: 0.56 | EI12: 0.75 | EJ12: 0.64 | EK12: 0.67 | EL12: 0.25 | EM12: 0.59 | EN12: 0.75 | EO12: 0.49 | EP12: 0.75 | EQ12: 0.36 | ER12: 0.67 | ES12: 0.5 | ET12: 0.62 | EU12: 0.83 | EV12: 0.58 | EW12: 0.75 | EX12: 0.36 | EY12: 0.67 | EZ12: 0.5
A13: JOR | B13: Jordan | C13: 0.55 | D13: 0.54 | E13: 0.62 | F13: 0.5 | G13: 0.64 | H13: 0.58 | I13: 0.42 | J13: 0.57 | K13: 0.54 | L13: 0.65 | M13: 0.5 | N13: 0.64 | O13: 0.58 | P13: 0.5 | Q13: 0.57 | R13: 0.58 | S13: 0.63 | T13: 0.5 | U13: 0.59 | V13: 0.58 | W13: 0.5 | X13: 0.56 | Y13: 0.58 | Z13: 0.62 | AA13: 0.5 | AB13: 0.59 | AC13: 0.58 | AD13: 0.5 | AE13: 0.57 | AF13: 0.58 | AG13: 0.61 | AH13: 0.5 | AI13: 0.64 | AJ13: 0.58 | AK13: 0.5 | AL13: 0.59 | AM13: 0.63 | AN13: 0.61 | AO13: 0.5 | AP13: 0.64 | AQ13: 0.67 | AR13: 0.5 | AS13: 0.61 | AT13: 0.63 | AU13: 0.62 | AV13: 0.5 | AW13: 0.73 | AX13: 0.67 | AY13: 0.5 | AZ13: 0.61 | BA13: 0.63 | BB13: 0.62 | BC13: 0.5 | BD13: 0.73 | BE13: 0.67 | BF13: 0.5 | BG13: 0.6 | BH13: 0.63 | BI13: 0.69 | BJ13: 0.5 | BK13: 0.73 | BL13: 0.67 | BM13: 0.42 | BN13: 0.59 | BO13: 0.63 | BP13: 0.66 | BQ13: 0.5 | BR13: 0.68 | BS13: 0.67 | BT13: 0.42 | BU13: 0.63 | BV13: 0.63 | BW13: 0.67 | BX13: 0.5 | BY13: 0.82 | BZ13: 0.67 | CA13: 0.5 | CB13: 0.65 | CC13: 0.67 | CD13: 0.76 | CE13: 0.5 | CF13: 0.82 | CG13: 0.67 | CH13: 0.5 | CI13: 0.66 | CJ13: 0.67 | CK13: 0.8 | CL13: 0.5 | CM13: 0.82 | CN13: 0.67 | CO13: 0.5 | CP13: 0.66 | CQ13: 0.67 | CR13: 0.82 | CS13: 0.5 | CT13: 0.82 | CU13: 0.67 | CV13: 0.5 | CW13: 0.67 | CX13: 0.67 | CY13: 0.85 | CZ13: 0.5 | DA13: 0.82 | DB13: 0.67 | DC13: 0.5 | DD13: 0.69 | DE13: 0.79 | DF13: 0.86 | DG13: 0.5 | DH13: 0.82 | DI13: 0.67 | DJ13: 0.5 | DK13: 0.68 | DL13: 0.79 | DM13: 0.83 | DN13: 0.5 | DO13: 0.82 | DP13: 0.67 | DQ13: 0.5 | DR13: 0.68 | DS13: 0.79 | DT13: 0.83 | DU13: 0.5 | DV13: 0.77 | DW13: 0.67 | DX13: 0.5 | DY13: 0.67 | DZ13: 0.79 | EA13: 0.8 | EB13: 0.5 | EC13: 0.77 | ED13: 0.67 | EE13: 0.5 | EF13: 0.66 | EG13: 0.75 | EH13: 0.79 | EI13: 0.5 | EJ13: 0.77 | EK13: 0.67 | EL13: 0.5 | EM13: 0.67 | EN13: 0.75 | EO13: 0.78 | EP13: 0.5 | EQ13: 0.82 | ER13: 0.67 | ES13: 0.5 | ET13: 0.71 | EU13: 0.75 | EV13: 0.84 | EW13: 0.5 | EX13: 0.82 | EY13: 0.67 | EZ13: 0.67
... A29: ZMB | B29: Zambia | C29: 0.56 | D29: 0.79 | E29: 0.73 | F29: 0.25 | G29: 0.59 | H29: 0.67 | I29: 0.33 | J29: 0.53 | K29: 0.75 | L29: 0.71 | M29: 0.25 | N29: 0.45 | O29: 0.67 | P29: 0.33 | Q29: 0.54 | R29: 0.75 | S29: 0.71 | T29: 0.25 | U29: 0.45 | V29: 0.67 | W29: 0.42 | X29: 0.54 | Y29: 0.75 | Z29: 0.72 | AA29: 0.25 | AB29: 0.5 | AC29: 0.67 | AD29: 0.33 | AE29: 0.55 | AF29: 0.75 | AG29: 0.74 | AH29: 0.25 | AI29: 0.55 | AJ29: 0.67 | AK29: 0.33 | AL29: 0.57 | AM29: 0.75 | AN29: 0.77 | AO29: 0.25 | AP29: 0.55 | AQ29: 0.67 | AR29: 0.42 | AS29: 0.56 | AT29: 0.75 | AU29: 0.73 | AV29: 0.25 | AW29: 0.55 | AX29: 0.67 | AY29: 0.42 | AZ29: 0.55 | BA29: 0.75 | BB29: 0.71 | BC29: 0.25 | BD29: 0.5 | BE29: 0.67 | BF29: 0.42 | BG29: 0.55 | BH29: 0.75 | BI29: 0.71 | BJ29: 0.25 | BK29: 0.5 | BL29: 0.67 | BM29: 0.42 | BN29: 0.55 | BO29: 0.75 | BP29: 0.79 | BQ29: 0.25 | BR29: 0.45 | BS29: 0.67 | BT29: 0.42 | BU29: 0.56 | BV29: 0.75 | BW29: 0.77 | BX29: 0.25 | BY29: 0.45 | BZ29: 0.67 | CA29: 0.5 | CB29: 0.57 | CC29: 0.75 | CD29: 0.78 | CE29: 0.25 | CF29: 0.45 | CG29: 0.67 | CH29: 0.5 | CI29: 0.57 | CJ29: 0.75 | CK29: 0.78 | CL29: 0.25 | CM29: 0.45 | CN29: 0.67 | CO29: 0.5 | CP29: 0.57 | CQ29: 0.75 | CR29: 0.79 | CS29: 0.25 | CT29: 0.45 | CU29: 0.67 | CV29: 0.5 | CW29: 0.58 | CX29: 0.75 | CY29: 0.78 | CZ29: 0.25 | DA29: 0.45 | DB29: 0.67 | DC29: 0.58 | DD29: 0.57 | DE29: 0.75 | DF29: 0.77 | DG29: 0.25 | DH29: 0.5 | DI29: 0.67 | DJ29: 0.5 | DK29: 0.59 | DL29: 0.79 | DM29: 0.78 | DN29: 0.25 | DO29: 0.55 | DP29: 0.67 | DQ29: 0.5 | DR29: 0.57 | DS29: 0.79 | DT29: 0.78 | DU29: 0.25 | DV29: 0.45 | DW29: 0.67 | DX29: 0.5 | DY29: 0.52 | DZ29: 0.75 | EA29: 0.69 | EB29: 0.25 | EC29: 0.45 | ED29: 0.67 | EE29: 0.33 | EF29: 0.51 | EG29: 0.75 | EH29: 0.61 | EI29: 0.25 | EJ29: 0.45 | EK29: 0.67 | EL29: 0.33 | EM29: 0.6 | EN29: 0.75 | EO29: 0.78 | EP29: 0.25 | EQ29: 0.82 | ER29: 0.67 | ES29: 0.33 | ET29: 0.65 | EU29: 0.75 | EV29: 0.89 | EW29: 0.25 | EX29: 0.82 | EY29: 0.67 | EZ29: 0.5
E37: PRS21VA | F37: meaning
E38: PRS-data source PRS org ICRG
E40: VA | F40: Voice and Accountability (Military in politics, Democratic accountability)
E42: PV | F42: Political Stability and Absence of Violence (Government stability, Internal conflict, External conflict, Ethnic tensions)
E44: GE | F44: Government Effectiveness (Bureaucratic quality)
E46: RQ | F46: Regulatory Quality (Investment profile)
E48: RL | F48: Rule of Law (Law and order)
E50: CC | F50: Control of Corruption (Corruption)

Sheet Graphs of FD & INST

Sheet FDxINST
A1: Country | C1: Country code | D1: Data type | E1: 2000 [YR2000] | F1: 2001 [YR2001] | G1: 2002 [YR2002] | H1: 2003 [YR2003] | I1: 2004 [YR2004] | J1: 2005 [YR2005] | K1: 2006 [YR2006] | L1: 2007 [YR2007] | M1: 2008 [YR2008] | N1: 2009 [YR2009] | O1: 2010 [YR2010] | P1: 2011 [YR2011] | Q1: 2012 [YR2012] | R1: 2013 [YR2013] | S1: 2014 [YR2014] | T1: 2015 [YR2015] | U1: 2016 [YR2016] | V1: 2017 [YR2017] | W1: 2018 [YR2018] | X1: 2019 [YR2019] | Y1: 2020 [YR2020] | Z1: 2021 [YR2021] | AB1: Average
A2: Angola | C2: AGO | D2: FD*INST | E2: =FD!E2*INST!B2 -> 0.0342 | F2: =FD!F2*INST!C2 -> 0.0324 | G2: =FD!G2*INST!D2 -> 0.046 | H2: =FD!H2*INST!E2 -> 0.048 | I2: =FD!I2*INST!F2 -> 0.0506 | J2: =FD!J2*INST!G2 -> 0.0506 | K2: =FD!K2*INST!H2 -> 0.0564 | L2: =FD!L2*INST!I2 -> 0.0624 | ... Z2: =FD!Z2*INST!W2 -> 0.0686 | AB2: =AVERAGE(E2:Z2) -> 0.05775
A3: Bangladesh | C3: BGD | D3: FD*INST | E3: =FD!E3*INST!B3 -> 0.121 | F3: =FD!F3*INST!C3 -> 0.095 | G3: =FD!G3*INST!D3 -> 0.08 | H3: =FD!H3*INST!E3 -> 0.084 | I3: =FD!I3*INST!F3 -> 0.0798 | J3: =FD!J3*INST!G3 -> 0.0752 | K3: =FD!K3*INST!H3 -> 0.063 | L3: =FD!L3*INST!I3 -> 0.0705 | ... Z3: =FD!Z3*INST!W3 -> 0.1224 | AB3: =AVERAGE(E3:Z3) -> 0.10241818
A4: Bolivia | C4: BOL | D4: FD*INST | E4: =FD!E4*INST!B4 -> 0.066 | F4: =FD!F4*INST!C4 -> 0.0671 | G4: =FD!G4*INST!D4 -> 0.0672 | H4: =FD!H4*INST!E4 -> 0.0855 | I4: =FD!I4*INST!F4 -> 0.078 | J4: =FD!J4*INST!G4 -> 0.075 | K4: =FD!K4*INST!H4 -> 0.0768 | L4: =FD!L4*INST!I4 -> 0.0846 | ... Z4: =FD!Z4*INST!W4 -> 0.1833 | AB4: =AVERAGE(E4:Z4) -> 0.11207273
A5: Cameroon | C5: CMR | D5: FD*INST | E5: =FD!E5*INST!B5 -> 0.0384 | F5: =FD!F5*INST!C5 -> 0.036 | G5: =FD!G5*INST!D5 -> 0.0344 | H5: =FD!H5*INST!E5 -> 0.0294 | I5: =FD!I5*INST!F5 -> 0.0329 | J5: =FD!J5*INST!G5 -> 0.0392 | K5: =FD!K5*INST!H5 -> 0.0432 | L5: =FD!L5*INST!I5 -> 0.0495 | ... Z5: =FD!Z5*INST!W5 -> 0.041 | AB5: =AVERAGE(E5:Z5) -> 0.03915
A6: Congo, Rep. of | C6: COG | D6: FD*INST | E6: =FD!E6*INST!B6 -> 0.014 | F6: =FD!F6*INST!C6 -> 0.021 | G6: =FD!G6*INST!D6 -> 0.0172 | H6: =FD!H6*INST!E6 -> 0.0252 | I6: =FD!I6*INST!F6 -> 0.0172 | J6: =FD!J6*INST!G6 -> 0.0129 | K6: =FD!K6*INST!H6 -> 0.0132 | L6: =FD!L6*INST!I6 -> 0.0132 | ... Z6: =FD!Z6*INST!W6 -> 0.0378 | AB6: =AVERAGE(E6:Z6) -> 0.031454545
A7: Côte d'Ivoire | C7: CIV | D7: FD*INST | E7: =FD!E7*INST!B7 -> 0.0784 | F7: =FD!F7*INST!C7 -> 0.0408 | G7: =FD!G7*INST!D7 -> 0.035 | H7: =FD!H7*INST!E7 -> 0.037 | I7: =FD!I7*INST!F7 -> 0.0352 | J7: =FD!J7*INST!G7 -> 0.0319 | K7: =FD!K7*INST!H7 -> 0.0403 | L7: =FD!L7*INST!I7 -> 0.0462 | ... Z7: =FD!Z7*INST!W7 -> 0.0559 | AB7: =AVERAGE(E7:Z7) -> 0.052154545
A8: Egypt, Arab Rep. of | C8: EGY | D8: FD*INST | E8: =FD!E8*INST!B8 -> 0.174 | F8: =FD!F8*INST!C8 -> 0.1829 | G8: =FD!G8*INST!D8 -> 0.1749 | H8: =FD!H8*INST!E8 -> 0.1782 | I8: =FD!I8*INST!F8 -> 0.1802 | J8: =FD!J8*INST!G8 -> 0.2268 | K8: =FD!K8*INST!H8 -> 0.1998 | L8: =FD!L8*INST!I8 -> 0.1924 | ... Z8: =FD!Z8*INST!W8 -> 0.1612 | AB8: =AVERAGE(E8:Z8) -> 0.16442273
A9: Ghana | C9: GHA | D9: FD*INST | E9: =FD!E9*INST!B9 -> 0.0648 | F9: =FD!F9*INST!C9 -> 0.06 | G9: =FD!G9*INST!D9 -> 0.0539 | H9: =FD!H9*INST!E9 -> 0.0588 | I9: =FD!I9*INST!F9 -> 0.0728 | J9: =FD!J9*INST!G9 -> 0.066 | K9: =FD!K9*INST!H9 -> 0.0627 | L9: =FD!L9*INST!I9 -> 0.0672 | ... Z9: =FD!Z9*INST!W9 -> 0.1026 | AB9: =AVERAGE(E9:Z9) -> 0.079522727
A10: Haiti | C10: HTI | D10: FD*INST | E10: =FD!E10*INST!B10 -> 0.0288 | F10: =FD!F10*INST!C10 -> 0.0306 | G10: =FD!G10*INST!D10 -> 0.027 | H10: =FD!H10*INST!E10 -> 0.0261 | I10: =FD!I10*INST!F10 -> 0.027 | J10: =FD!J10*INST!G10 -> 0.015 | K10: =FD!K10*INST!H10 -> 0.0138 | L10: =FD!L10*INST!I10 -> 0.0174 | ... Z10: =FD!Z10*INST!W10 -> 0.028 | AB10: =AVERAGE(E10:Z10) -> 0.025281818
A11: Honduras | C11: HND | D11: FD*INST | E11: =FD!E11*INST!B11 -> 0.0676 | F11: =FD!F11*INST!C11 -> 0.0795 | G11: =FD!G11*INST!D11 -> 0.0742 | H11: =FD!H11*INST!E11 -> 0.0848 | I11: =FD!I11*INST!F11 -> 0.0765 | J11: =FD!J11*INST!G11 -> 0.0816 | K11: =FD!K11*INST!H11 -> 0.0918 | L11: =FD!L11*INST!I11 -> 0.095 | ... Z11: =FD!Z11*INST!W11 -> 0.1092 | AB11: =AVERAGE(E11:Z11) -> 0.094509091
A12: India | C12: IND | D12: FD*INST | E12: =FD!E12*INST!B12 -> 0.2728 | F12: =FD!F12*INST!C12 -> 0.2478 | G12: =FD!G12*INST!D12 -> 0.2666 | H12: =FD!H12*INST!E12 -> 0.2709 | I12: =FD!I12*INST!F12 -> 0.3015 | J12: =FD!J12*INST!G12 -> 0.3015 | K12: =FD!K12*INST!H12 -> 0.3102 | L12: =FD!L12*INST!I12 -> 0.2925 | ... Z12: =FD!Z12*INST!W12 -> 0.3604 | AB12: =AVERAGE(E12:Z12) -> 0.29815909
A13: Jordan | C13: JOR | D13: FD*INST | E13: =FD!E13*INST!B13 -> 0.3763 | F13: =FD!F13*INST!C13 -> 0.3551 | G13: =FD!G13*INST!D13 -> 0.3498 | H13: =FD!H13*INST!E13 -> 0.3484 | I13: =FD!I13*INST!F13 -> 0.3604 | J13: =FD!J13*INST!G13 -> 0.3672 | K13: =FD!K13*INST!H13 -> 0.345 | L13: =FD!L13*INST!I13 -> 0.3417 | ... Z13: =FD!Z13*INST!W13 -> 0.198 | AB13: =AVERAGE(E13:Z13) -> 0.28574545
... A28: Zambia | C28: ZMB | D28: FD*INST | E28: =FD!E28*INST!B28 -> 0.091 | F28: =FD!F28*INST!C28 -> 0.084 | G28: =FD!G28*INST!D28 -> 0.0867 | H28: =FD!H28*INST!E28 -> 0.0728 | I28: =FD!I28*INST!F28 -> 0.0912 | J28: =FD!J28*INST!G28 -> 0.0885 | K28: =FD!K28*INST!H28 -> 0.0969 | L28: =FD!L28*INST!I28 -> 0.1044 | ... Z28: =FD!Z28*INST!W28 -> 0.112 | AB28: =AVERAGE(E28:Z28) -> 0.098318182

Sheet REN
A1: Country Name | B1: 2000 [YR2000] | C1: 2001 [YR2001] | D1: 2002 [YR2002] | E1: 2003 [YR2003] | F1: 2004 [YR2004] | G1: 2005 [YR2005] | H1: 2006 [YR2006] | I1: 2007 [YR2007] | J1: 2008 [YR2008] | K1: 2009 [YR2009] | L1: 2010 [YR2010] | M1: 2011 [YR2011] | N1: 2012 [YR2012] | O1: 2013 [YR2013] | P1: 2014 [YR2014] | Q1: 2015 [YR2015] | R1: 2016 [YR2016] | S1: 2017 [YR2017] | T1: 2018 [YR2018] | U1: 2019 [YR2019] | V1: 2020 [YR2020] | W1: 2021 [YR2021] | Y1: average
A2: Angola | B2: 73.8 | C2: 72.8 | D2: 70.8 | E2: 65.6 | F2: 62.3 | G2: 68.9 | H2: 62.6 | I2: 58.9 | J2: 55.4 | K2: 53 | L2: 53.1 | M2: 51.7 | N2: 49 | O2: 46.8 | P2: 47.5 | Q2: 47.1 | R2: 48.1 | S2: 52.5 | T2: 52.5 | U2: 51 | V2: 60.1 | W2: 52.9 | Y2: =AVERAGE(B2:W2) -> 57.109091
A3: Bangladesh | B3: 60.2 | C3: 55.9 | D3: 54.4 | E3: 52.6 | F3: 52 | G3: 50.6 | H3: 48.6 | I3: 47.2 | J3: 45.2 | K3: 43.1 | L3: 40.3 | M3: 38.4 | N3: 37.3 | O3: 37 | P3: 35.4 | Q3: 33.1 | R3: 30.2 | S3: 28.1 | T3: 27 | U3: 26.1 | V3: 27.2 | W3: 25 | Y3: =AVERAGE(B3:W3) -> 40.677273
A4: Bolivia | B4: 29.2 | C4: 29 | D4: 28.1 | E4: 27 | F4: 25.8 | G4: 24.6 | H4: 23.7 | I4: 22.1 | J4: 21.3 | K4: 20.6 | L4: 19.9 | M4: 18.1 | N4: 17.4 | O4: 16 | P4: 15 | Q4: 14.2 | R4: 13.6 | S4: 14.3 | T4: 14.3 | U4: 13.5 | V4: 16.9 | W4: 12.8 | Y4: =AVERAGE(B4:W4) -> 19.881818
A5: Cameroon | B5: 84.6 | C5: 85.3 | D5: 85.2 | E5: 85.3 | F5: 85.5 | G5: 86.3 | H5: 85.5 | I5: 80.8 | J5: 80.8 | K5: 79.2 | L5: 78.7 | M5: 78.6 | N5: 78.6 | O5: 77.7 | P5: 76.9 | Q5: 78.1 | R5: 78.8 | S5: 79.2 | T5: 78.7 | U5: 78.9 | V5: 78.9 | W5: 79.2 | Y5: =AVERAGE(B5:W5) -> 80.945455
A6: Congo, Rep. | B6: 64.9 | C6: 61.2 | D6: 68.6 | E6: 62.1 | F6: 63.1 | G6: 63.1 | H6: 69.3 | I6: 60.2 | J6: 56.8 | K6: 55.9 | L6: 54.5 | M6: 64.3 | N6: 65.1 | O6: 62.3 | P6: 62.1 | Q6: 64.2 | R6: 67.7 | S6: 69.8 | T6: 70.6 | U6: 69.8 | V6: 71.4 | W6: 71.4 | Y6: =AVERAGE(B6:W6) -> 64.472727
A7: Cote d'Ivoire | B7: 63.7 | C7: 64.7 | D7: 65.3 | E7: 70.3 | F7: 75.4 | G7: 77.9 | H7: 74.8 | I7: 76.3 | J7: 74.2 | K7: 73.7 | L7: 75.4 | M7: 79.1 | N7: 74.9 | O7: 72.2 | P7: 71.9 | Q7: 64.5 | R7: 64 | S7: 62.5 | T7: 60.5 | U7: 61.1 | V7: 61.8 | W7: 58.2 | Y7: =AVERAGE(B7:W7) -> 69.2
A8: Egypt, Arab Rep. | B8: 8.3 | C8: 7.8 | D8: 7.3 | E8: 7.4 | F8: 7.6 | G8: 6.5 | H8: 6.2 | I8: 6 | J8: 5.9 | K8: 5.7 | L8: 5.4 | M8: 5.4 | N8: 5.3 | O8: 5.3 | P8: 5.4 | Q8: 5.3 | R8: 5.1 | S8: 4.9 | T8: 5 | U8: 6.2 | V8: 6.7 | W8: 6.1 | Y8: =AVERAGE(B8:W8) -> 6.1272727
A9: Ghana | B9: 71.6 | C9: 69.3 | D9: 65.7 | E9: 64.5 | F9: 62.4 | G9: 61.4 | H9: 58.6 | I9: 54.5 | J9: 57.3 | K9: 51.9 | L9: 51.9 | M9: 50.1 | N9: 46.5 | O9: 46.2 | P9: 47.7 | Q9: 44 | R9: 45.2 | S9: 45.3 | T9: 42.1 | U9: 42.6 | V9: 40 | W9: 39 | Y9: =AVERAGE(B9:W9) -> 52.627273
A10: Haiti | B10: 80.8 | C10: 80.9 | D10: 79.1 | E10: 79 | F10: 81.1 | G10: 81.1 | H10: 81.4 | I10: 79.3 | J10: 79.6 | K10: 80.3 | L10: 79 | M10: 79 | N10: 82.2 | O10: 80.4 | P10: 77.8 | Q10: 76.1 | R10: 76.1 | S10: 76.2 | T10: 76.2 | U10: 76.4 | V10: 76.3 | W10: 76.7 | Y10: =AVERAGE(B10:W10) -> 78.863636
A11: Honduras | B11: 55.2 | C11: 50.4 | D11: 49.8 | E11: 47.9 | F11: 46.7 | G11: 51.4 | H11: 52.2 | I11: 50.6 | J11: 50 | K11: 50.5 | L11: 53.6 | M11: 50.9 | N11: 49.3 | O11: 51.1 | P11: 52.2 | Q11: 50.8 | R11: 52.7 | S11: 45.6 | T11: 48.9 | U11: 46.2 | V11: 50.2 | W11: 45.9 | Y11: =AVERAGE(B11:W11) -> 50.095455
A12: India | B12: 46.9 | C12: 47.1 | D12: 45.8 | E12: 45.6 | F12: 44.9 | G12: 44.2 | H12: 43.2 | I12: 41.5 | J12: 39.4 | K12: 37.4 | L12: 36.2 | M12: 35 | N12: 34.8 | O12: 34.9 | P12: 33.9 | Q12: 33.4 | R12: 33 | S12: 32.5 | T12: 32.9 | U12: 33.5 | V12: 36.1 | W12: 34.9 | Y12: =AVERAGE(B12:W12) -> 38.504545
A13: Jordan | B13: 2.1 | C13: 2.1 | D13: 2.1 | E13: 2 | F13: 1.8 | G13: 1.7 | H13: 2.3 | I13: 2.3 | J13: 2.7 | K13: 2.8 | L13: 3 | M13: 3 | N13: 2.9 | O13: 3.1 | P13: 3.1 | Q13: 3.2 | R13: 4.7 | S13: 5.3 | T13: 7.2 | U13: 8.5 | V13: 10.7 | W13: 11.5 | Y13: =AVERAGE(B13:W13) -> 4.0045455
... A28: Zambia | B28: 90 | C28: 89.8 | D28: 89.6 | E28: 89.3 | F28: 89.4 | G28: 88.9 | H28: 89.7 | I28: 90.7 | J28: 89.8 | K28: 89.2 | L28: 89.2 | M28: 87.9 | N28: 85.4 | O28: 85.3 | P28: 84.6 | Q28: 84 | R28: 84 | S28: 83.5 | T28: 83.8 | U28: 86.1 | V28: 85.4 | W28: 83 | Y28: =AVERAGE(B28:W28) -> 87.209091

Sheet RGDPPC
A1: Series Name | B1: Series Code | C1: Country Name | D1: Country Code | E1: 2000 [YR2000] | F1: 2001 [YR2001] | G1: 2002 [YR2002] | H1: 2003 [YR2003] | I1: 2004 [YR2004] | J1: 2005 [YR2005] | K1: 2006 [YR2006] | L1: 2007 [YR2007] | M1: 2008 [YR2008] | N1: 2009 [YR2009] | O1: 2010 [YR2010] | P1: 2011 [YR2011] | Q1: 2012 [YR2012] | R1: 2013 [YR2013] | S1: 2014 [YR2014] | T1: 2015 [YR2015] | U1: 2016 [YR2016] | V1: 2017 [YR2017] | W1: 2018 [YR2018] | X1: 2019 [YR2019] | Y1: 2020 [YR2020] | Z1: 2021 [YR2021] | AB1: Average
A2: GDP per capita (constant 2015 US$) | B2: NY.GDP.PCAP.KD | C2: Angola | D2: AGO | E2: 3736444.5 | F2: 3794145.8 | G2: 4579054.7 | H2: 4529217.3 | I2: 5188677.9 | J2: 6382750.4 | K2: 7378030.5 | L2: 8898538.8 | M2: 10197086 | N2: 9613777.9 | O2: 9701331.7 | P2: 9609642.2 | Q2: 10475417 | R2: 10684000 | S2: 10894852 | T2: 10329170 | U2: 9126340.3 | V2: 8477419.5 | W2: 7704768.2 | X2: 7099232.6 | Y2: 5921320.6 | Z2: 5690366.1 | AB2: =AVERAGE(E2:Z2) -> 7727799.3
A3: GDP per capita (constant 2015 US$) | B3: NY.GDP.PCAP.KD | C3: Bangladesh | D3: BGD | E3: 385095.3 | F3: 411251.48 | G3: 429905.95 | H3: 458093.78 | I3: 493725.96 | J3: 546422.14 | K3: 607494.87 | L3: 681463.84 | M3: 750749.74 | N3: 813116.32 | O3: 890502.18 | P3: 991179.43 | Q3: 1103322.1 | R3: 1216955.3 | S3: 1344225.8 | T3: 1499122.2 | U3: 1689560.4 | V3: 1887199.1 | W3: 2138176.5 | X3: 2446746.7 | Y3: 2574952.7 | Z3: 2897077.3 | AB3: =AVERAGE(E3:Z3) -> 1193470
A4: GDP per capita (constant 2015 US$) | B4: NY.GDP.PCAP.KD | C4: Bolivia | D4: BOL | E4: 4056962.3 | F4: 4055574.9 | G4: 4119560 | H4: 4202792.5 | I4: 4409961.4 | J4: 4649141.1 | K4: 4934738.9 | L4: 5214040.4 | M4: 5679882.1 | N4: 5868873.5 | O4: 6157380.7 | P4: 6597297.6 | Q4: 7060918.3 | R4: 7803723.6 | S4: 8415234.8 | T4: 8976093.3 | U4: 9471440.6 | V4: 9986637.8 | W4: 10541479 | X4: 10708482 | Y4: 8701435.4 | Z4: 9599776.6 | AB4: =AVERAGE(E4:Z4) -> 6873246.7
A5: GDP per capita (constant 2015 US$) | B5: NY.GDP.PCAP.KD | C5: Cameroon | D5: CMR | E5: 1325438.5 | F5: 1368728.5 | G5: 1416021.6 | H5: 1491071.7 | I5: 1617330.9 | J5: 1599576 | K5: 1631571.7 | L5: 1678918 | M5: 1677082.3 | N5: 1666421.8 | O5: 1666426.4 | P5: 1683004.1 | Q5: 1741527.9 | R5: 1814983 | S5: 1909424.8 | T5: 2002225.3 | U5: 2060999.9 | V5: 2087755.7 | W5: 2134578.6 | X5: 2161834.6 | Y5: 2057845.2 | Z5: 2083911.7 | AB5: =AVERAGE(E5:Z5) -> 1767121.7
A6: GDP per capita (constant 2015 US$) | B6: NY.GDP.PCAP.KD | C6: Congo, Rep. | D6: COG | E6: 4231328.1 | F6: 4227814.8 | G6: 4410708.9 | H6: 4239015 | I6: 4239003.4 | J6: 4579757.8 | K6: 4955180 | L6: 4016421 | M6: 4250022.6 | N6: 4889917.2 | O6: 5439553.7 | P6: 5324527.8 | Q6: 6086390.1 | R6: 5715243.5 | S6: 6193534 | T6: 5950437.7 | U6: 4727115.6 | V6: 4013095.5 | W6: 3647932.1 | X6: 3555151 | Y6: 2977386.1 | Z6: 2896091.3 | AB6: =AVERAGE(E6:Z6) -> 4571164.9
A7: GDP per capita (constant 2015 US$) | B7: NY.GDP.PCAP.KD | C7: Cote d'Ivoire | D7: CIV | E7: 2951365.5 | F7: 2678371.8 | G7: 2406467.3 | H7: 2078176 | I7: 2107913.3 | J7: 2049860 | K7: 2067195.6 | L7: 2016893.9 | M7: 2115940.6 | N7: 2172435.4 | O7: 2373230.4 | P7: 2034801.4 | Q7: 2260314.8 | R7: 2664491.9 | S7: 3036435 | T7: 3293203.4 | U7: 3569370.5 | V7: 3891996.3 | W7: 4053469.8 | X7: 4381067.4 | Y7: 4223373.7 | Z7: 4607360.7 | AB7: =AVERAGE(E7:Z7) -> 2865169.8
A8: GDP per capita (constant 2015 US$) | B8: NY.GDP.PCAP.KD | C8: Egypt, Arab Rep. | D8: EGY | E8: 6044755 | F8: 6210235.5 | G8: 6242408.4 | H8: 6374639.1 | I8: 6627655.9 | J8: 6946930.6 | K8: 7626567.7 | L8: 8421984.7 | M8: 9316004.1 | N8: 9828830.8 | O8: 10457755 | P8: 10383710 | Q8: 10374789 | R8: 10345090 | S8: 10469512 | T8: 10936127 | U8: 11432665 | V8: 11922585 | W8: 12735189 | X8: 13699212 | Y8: 14219457 | Z8: 14725024 | AB8: =AVERAGE(E8:Z8) -> 9788233
A9: GDP per capita (constant 2015 US$) | B9: NY.GDP.PCAP.KD | C9: Ghana | D9: GHA | E9: 1043745 | F9: 1070359.5 | G9: 1106304.9 | H9: 1159990.5 | I9: 1226809.5 | J9: 1305533.8 | K9: 1403105.1 | L9: 1450979.8 | M9: 1643101.4 | N9: 1718232 | O9: 1905414.5 | P9: 2361939.8 | Q9: 2688021.8 | R9: 2949897.2 | S9: 2976639 | T9: 2964249.7 | U9: 3026648.6 | V9: 3386701.3 | W9: 3664391.4 | X9: 3993235.3 | Y9: 3876830.3 | Z9: 4115964.8 | AB9: =AVERAGE(E9:Z9) -> 2319913.4
A10: GDP per capita (constant 2015 US$) | B10: NY.GDP.PCAP.KD | C10: Haiti | D10: HTI | E10: 1803366.7 | F10: 1726896.1 | G10: 1701796.9 | H10: 1759526.9 | I10: 1656118.9 | J10: 1701284.7 | K10: 1703124.5 | L10: 1805290.8 | M10: 1840184.5 | N10: 1996276.6 | O10: 1736027.3 | P10: 1874624.3 | Q10: 1835714.6 | R10: 1938727.8 | S10: 1993089.9 | T10: 1991279 | U10: 2007177.2 | V10: 2052549.9 | W10: 2065982.3 | X10: 1944410.3 | Y10: 1773419 | Z10: 1671123.8 | AB10: =AVERAGE(E10:Z10) -> 1844454.2
A11: GDP per capita (constant 2015 US$) | B11: NY.GDP.PCAP.KD | C11: Honduras | D11: HND | E11: 3202231.5 | F11: 3201194.3 | G11: 3268766.6 | H11: 3394060.1 | I11: 3643935.5 | J11: 3904008.8 | K11: 4229335.9 | L11: 4554790 | M11: 4731264.9 | N11: 4311057.4 | O11: 4445659 | P11: 4599149 | Q11: 4789067.4 | R11: 4863794.7 | S11: 4969545.4 | T11: 5158361.5 | U11: 5362604.6 | V11: 5680471.5 | W11: 5905556.3 | X11: 5990826.5 | Y11: 4793611.1 | Z11: 5874643.3 | AB11: =AVERAGE(E11:Z11) -> 4585178.9
A12: GDP per capita (constant 2015 US$) | B12: NY.GDP.PCAP.KD | C12: India | D12: IND | E12: 572601.11 | F12: 606073.74 | G12: 629826.22 | H12: 707750.18 | I12: 796728.72 | J12: 898197.02 | K12: 1016533.3 | L12: 1143289.1 | M12: 1180495.4 | N12: 1334259.8 | O12: 1525618.7 | P12: 1642525.6 | Q12: 1777145.7 | R12: 1958470.9 | S12: 2203195.2 | T12: 2509050.2 | U12: 2871212.8 | V12: 3199439.5 | W12: 3547036.3 | X12: 3748214.8 | Y12: 3263446.2 | Z12: 3862441.2 | AB12: =AVERAGE(E12:Z12) -> 1863343.3
A13: GDP per capita (constant 2015 US$) | B13: NY.GDP.PCAP.KD | C13: Jordan | D13: JOR | E13: 11642268 | F13: 12381717 | G13: 13283287 | H13: 13787497 | I13: 15485461 | J13: 17235892 | K13: 17722994 | L13: 18381390 | M13: 20159700 | N13: 21300354 | O13: 21358949 | P13: 21452432 | Q13: 21878783 | R13: 20761877 | S13: 18336541 | T13: 16343882 | U13: 15469646 | V13: 15529132 | W13: 15435236 | X13: 15359065 | Y13: 14492331 | Z13: 15010410 | AB13: =AVERAGE(E13:Z13) -> 16945856
... A28: GDP per capita (constant 2015 US$) | B28: NY.GDP.PCAP.KD | C28: Zambia | D28: ZMB | E28: 647195.53 | F28: 675718.42 | G28: 693924.28 | H28: 745891.65 | I28: 801875.94 | J28: 863188.26 | K28: 938115.38 | L28: 1026342.6 | M28: 1110043.7 | N28: 1233697.1 | O28: 1400476.1 | P28: 1460385.8 | Q28: 1584550.7 | R28: 1640372.1 | S28: 1687433.3 | T28: 1679299.5 | U28: 1699308.1 | V28: 1712874.4 | W28: 1745702.8 | X28: 1693072.9 | Y28: 1509789.7 | Z28: 1610635.7 | AB28: =AVERAGE(E28:Z28) -> 1279995.2

Sheet POP
A1: Series Name | B1: Series Code | C1: Country Name | D1: Country Code | E1: 2000 [YR2000] | F1: 2001 [YR2001] | G1: 2002 [YR2002] | H1: 2003 [YR2003] | I1: 2004 [YR2004] | J1: 2005 [YR2005] | K1: 2006 [YR2006] | L1: 2007 [YR2007] | M1: 2008 [YR2008] | N1: 2009 [YR2009] | O1: 2010 [YR2010] | P1: 2011 [YR2011] | Q1: 2012 [YR2012] | R1: 2013 [YR2013] | S1: 2014 [YR2014] | T1: 2015 [YR2015] | U1: 2016 [YR2016] | V1: 2017 [YR2017] | W1: 2018 [YR2018] | X1: 2019 [YR2019] | Y1: 2020 [YR2020] | Z1: 2021 [YR2021] | AB1: Average
A2: Population, total | B2: SP.POP.TOTL | C2: Angola | D2: AGO | E2: 16194869 | F2: 16747208 | G2: 17327699 | H2: 17943712 | I2: 18600423 | J2: 19291161 | K2: 20015279 | L2: 20778561 | M2: 21578655 | N2: 22414773 | O2: 23294825 | P2: 24218352 | Q2: 25177394 | R2: 26165620 | S2: 27160769 | T2: 28157798 | U2: 29183070 | V2: 30234839 | W2: 31297155 | X2: 32375632 | Y2: 33451132 | Z2: 34532429 | AB2: =AVERAGE(E2:Z2) -> 24370062
A3: Population, total | B3: SP.POP.TOTL | C3: Bangladesh | D3: BGD | E3: 135000000 | F3: 137000000 | G3: 139000000 | H3: 141000000 | I3: 143000000 | J3: 145000000 | K3: 146000000 | L3: 148000000 | M3: 149000000 | N3: 151000000 | O3: 152000000 | P3: 154000000 | Q3: 155000000 | R3: 157000000 | S3: 158000000 | T3: 159000000 | U3: 161000000 | V3: 162000000 | W3: 164000000 | X3: 165000000 | Y3: 166000000 | Z3: 168000000 | AB3: =AVERAGE(E3:Z3) -> 152500000
A4: Population, total | B4: SP.POP.TOTL | C4: Bolivia | D4: BOL | E4: 8606326 | F4: 8752736 | G4: 8900355 | H4: 9050700 | I4: 9204287 | J4: 9360754 | K4: 9521689 | L4: 9685960 | M4: 9850858 | N4: 10016275 | O4: 10182345 | P4: 10348929 | Q4: 10515807 | R4: 10682608 | S4: 10848888 | T4: 11014705 | U4: 11180020 | V4: 11344587 | W4: 11508368 | X4: 11671386 | Y4: 11816299 | Z4: 11937360 | AB4: =AVERAGE(E4:Z4) -> 10272784
A5: Population, total | B5: SP.POP.TOTL | C5: Cameroon | D5: CMR | E5: 14912631 | F5: 15309490 | G5: 15725528 | H5: 16160340 | I5: 16610487 | J5: 17074594 | K5: 17550407 | L5: 18049896 | M5: 18574056 | N5: 19113974 | O5: 19668066 | P5: 20232304 | Q5: 20809529 | R5: 21402376 | S5: 22059893 | T5: 22763414 | U5: 23454161 | V5: 24128601 | W5: 24806383 | X5: 25506095 | Y5: 26210558 | Z5: 26915758 | AB5: =AVERAGE(E5:Z5) -> 20319934
A6: Population, total | B6: SP.POP.TOTL | C6: Congo, Rep. | D6: COG | E6: 3151345 | F6: 3272537 | G6: 3350771 | H6: 3445753 | I6: 3565554 | J6: 3696393 | K6: 3837409 | L6: 3980430 | M6: 4113517 | N6: 4281219 | O6: 4462290 | P6: 4609724 | Q6: 4740450 | R6: 4857099 | S6: 4975880 | T6: 5097581 | U6: 5222536 | V6: 5351011 | W6: 5483118 | X6: 5616661 | Y6: 5752791 | Z6: 5892183 | AB6: =AVERAGE(E6:Z6) -> 4488920.5
A7: Population, total | B7: SP.POP.TOTL | C7: Cote d'Ivoire | D7: CIV | E7: 17699004 | F7: 18178913 | G7: 18654771 | H7: 19125542 | I7: 19595000 | J7: 20068458 | K7: 20546802 | L7: 21030558 | M7: 21514439 | N7: 21997940 | O7: 22488065 | P7: 22982000 | Q7: 23467078 | R7: 23939775 | S7: 24527395 | T7: 25246342 | U7: 25989405 | V7: 26733372 | W7: 27464173 | X7: 28193009 | Y7: 28915449 | Z7: 29639736 | AB7: =AVERAGE(E7:Z7) -> 23090783
A8: Population, total | B8: SP.POP.TOTL | C8: Egypt, Arab Rep. | D8: EGY | E8: 73083284 | F8: 74652029 | G8: 76239137 | H8: 77853548 | I8: 79477443 | J8: 81101004 | K8: 82700403 | L8: 84276225 | M8: 85864789 | N8: 87501636 | O8: 89196072 | P8: 91093059 | Q8: 93161001 | R8: 95333553 | S8: 97528654 | T8: 99597342 | U8: 102000000 | V8: 104000000 | W8: 106000000 | X8: 108000000 | Y8: 109000000 | Z8: 111000000 | AB8: =AVERAGE(E8:Z8) -> 91302690
A9: Population, total | B9: SP.POP.TOTL | C9: Ghana | D9: GHA | E9: 19637087 | F9: 20167069 | G9: 20729388 | H9: 21296705 | I9: 21868298 | J9: 22449438 | K9: 23040702 | L9: 23642279 | M9: 24249946 | N9: 24862664 | O9: 25474995 | P9: 26095088 | Q9: 26734268 | R9: 27386193 | S9: 28041592 | T9: 28696068 | U9: 29356742 | V9: 30008354 | W9: 30637585 | X9: 31258945 | Y9: 31887809 | Z9: 32518665 | AB9: =AVERAGE(E9:Z9) -> 25910904
A10: Population, total | B10: SP.POP.TOTL | C10: Haiti | D10: HTI | E10: 8303151 | F10: 8455918 | G10: 8607641 | H10: 8759912 | I10: 8910263 | J10: 9061273 | K10: 9216562 | L10: 9373296 | M10: 9530774 | N10: 9689581 | O10: 9803294 | P10: 9914904 | Q10: 10069771 | R10: 10222362 | S10: 10373235 | T10: 10523242 | U10: 10671457 | V10: 10817754 | W10: 10962362 | X10: 11105163 | Y10: 11243848 | Z10: 11374586 | AB10: =AVERAGE(E10:Z10) -> 9863197.7
A11: Population, total | B11: SP.POP.TOTL | C11: Honduras | D11: HND | E11: 6577773 | F11: 6757993 | G11: 6938859 | H11: 7119213 | I11: 7298994 | J11: 7478355 | K11: 7656832 | L11: 7834798 | M11: 8012587 | N11: 8189899 | O11: 8365878 | P11: 8540583 | Q11: 8715076 | R11: 8889278 | S11: 9063122 | T11: 9237305 | U11: 9412380 | V11: 9588137 | W11: 9765210 | X11: 9943633 | Y11: 10119640 | Z11: 10289877 | AB11: =AVERAGE(E11:Z11) -> 8445246.5
A12: Population, total | B12: SP.POP.TOTL | C12: India | D12: IND | E12: 1060000000 | F12: 1080000000 | G12: 1100000000 | H12: 1120000000 | I12: 1140000000 | J12: 1150000000 | K12: 1170000000 | L12: 1190000000 | M12: 1210000000 | N12: 1230000000 | O12: 1240000000 | P12: 1260000000 | Q12: 1280000000 | R12: 1300000000 | S12: 1310000000 | T12: 1330000000 | U12: 1340000000 | V12: 1360000000 | W12: 1370000000 | X12: 1390000000 | Y12: 1400000000 | Z12: 1410000000 | AB12: =AVERAGE(E12:Z12) -> 1.2472727e+09
A13: Population, total | B13: SP.POP.TOTL | C13: Jordan | D13: JOR | E13: 5386945 | F13: 5498894 | G13: 5616066 | H13: 5741828 | I13: 5882061 | J13: 6029587 | K13: 6427371 | L13: 6827227 | M13: 6989866 | N13: 7141753 | O13: 7297043 | P13: 7480424 | Q13: 7587127 | R13: 7991809 | S13: 8791710 | T13: 9544729 | U13: 10006367 | V13: 10234226 | W13: 10462306 | X13: 10671891 | Y13: 10865228 | Z13: 11066356 | AB13: =AVERAGE(E13:Z13) -> 7888218.8
... A28: Population, total | B28: SP.POP.TOTL | C28: Zambia | D28: ZMB | E28: 10017631 | F28: 10325185 | G28: 10647949 | H28: 10983595 | I28: 11338198 | J28: 11718819 | K28: 12129553 | L28: 12565085 | M28: 13021324 | N28: 13490389 | O28: 13965594 | P28: 14437796 | Q28: 14913629 | R28: 15398997 | S28: 15895315 | T28: 16399089 | U28: 16914423 | V28: 17441320 | W28: 17973569 | X28: 18513839 | Y28: 19059395 | Z28: 19603607 | AB28: =AVERAGE(E28:Z28) -> 14397923
A32: Data from database: World Development Indicators
A33: Last Updated: 01/28/2025

Sheet FDI
A1: Series Name | B1: Series Code | C1: Country Name | D1: Country Code | E1: 2000 [YR2000] | F1: 2001 [YR2001] | G1: 2002 [YR2002] | H1: 2003 [YR2003] | I1: 2004 [YR2004] | J1: 2005 [YR2005] | K1: 2006 [YR2006] | L1: 2007 [YR2007] | M1: 2008 [YR2008] | N1: 2009 [YR2009] | O1: 2010 [YR2010] | P1: 2011 [YR2011] | Q1: 2012 [YR2012] | R1: 2013 [YR2013] | S1: 2014 [YR2014] | T1: 2015 [YR2015] | U1: 2016 [YR2016] | V1: 2017 [YR2017] | W1: 2018 [YR2018] | X1: 2019 [YR2019] | Y1: 2020 [YR2020] | Z1: 2021 [YR2021] | AB1: Average
A2: Foreign direct investment, net inflows (% of GDP) | B2: BX.KLT.DINV.WD.GD.ZS | C2: Angola | D2: AGO | E2: 9.623866 | F2: 24.00908 | G2: 11.40619 | H2: 20.08101 | I2: 9.329239 | J2: -3.52666 | K2: -0.072 | L2: -1.36876 | M2: 1.896314 | N2: 3.136661 | O2: -3.85111 | P2: -2.70487 | Q2: -1.14377 | R2: -5.38013 | S2: 2.690006 | T2: 11.08134 | U2: -0.34024 | V2: -10.0384 | W2: -8.12589 | X2: -5.78081 | Y2: -3.84826 | Z2: -6.54854 | AB2: =AVERAGE(E2:Z2) -> 1.8420121
A3: Foreign direct investment, net inflows (% of GDP) | B3: BX.KLT.DINV.WD.GD.ZS | C3: Bangladesh | D3: BGD | E3: 0.525362 | F3: 0.145444 | G3: 0.095579 | H3: 0.445961 | I3: 0.689472 | J3: 1.170652 | K3: 0.635864 | L3: 0.817757 | M3: 1.449658 | N3: 0.879517 | O3: 1.068968 | P3: 0.983399 | Q3: 1.188504 | R3: 1.73532 | S3: 1.468703 | T3: 1.450782 | U3: 0.879528 | V3: 0.616342 | W3: 0.753549 | X3: 0.543244 | Y3: 0.40786 | Z3: 0.414118 | AB3: =AVERAGE(E3:Z3) -> 0.83479923
A4: Foreign direct investment, net inflows (% of GDP) | B4: BX.KLT.DINV.WD.GD.ZS | C4: Bolivia | D4: BOL | E4: 8.76831 | F4: 8.668606 | G4: 8.557894 | H4: 2.442344 | I4: 0.745773 | J4: -2.49887 | K4: 2.451688 | L4: 2.791854 | M4: 3.072611 | N4: 2.439678 | O4: 3.165429 | P4: 3.584423 | Q4: 3.91355 | R4: 5.706622 | S4: 1.989825 | T4: 1.680728 | U4: 0.98808 | V4: 1.899493 | W4: 0.750525 | X4: -0.52974 | Y4: -3.08352 | Z4: 1.444278 | AB4: =AVERAGE(E4:Z4) -> 2.6795264
A5: Foreign direct investment, net inflows (% of GDP) | B5: BX.KLT.DINV.WD.GD.ZS | C5: Cameroon | D5: CMR | E5: 1.511445 | F5: -0.10653 | G5: 4.068985 | H5: 2.096944 | I5: 0.361118 | J5: 1.248608 | K5: 0.28274 | L5: 0.792291 | M5: 0.075755 | N5: 2.67167 | O5: 1.949524 | P5: 2.132704 | Q5: 1.74884 | R5: 1.622968 | S5: 1.994843 | T5: 2.15564 | U5: 1.963349 | V5: 2.25621 | W5: 1.914858 | X5: 2.583406 | Y5: 1.655956 | Z5: 2.140613 | AB5: =AVERAGE(E5:Z5) -> 1.6873608
A6: Foreign direct investment, net inflows (% of GDP) | B6: BX.KLT.DINV.WD.GD.ZS | C6: Congo, Rep. | D6: COG | E6: -3.04039 | F6: -4.84426 | G6: 6.594565 | H6: 6.280146 | I6: 1.901621 | J6: 12.04985 | K6: 18.44598 | L6: 16.21656 | M6: 16.721 | N6: 12.22889 | O6: 11.5773 | P6: 1.907835 | Q6: -0.3914 | R6: 10.4621 | S6: 16.134 | T6: 34.41826 | U6: 0.462969 | V6: 0.379684 | W6: 0.092155 | X6: -10.2148 | Y6: -17.2921 | Z6: -2.15983 | AB6: =AVERAGE(E6:Z6) -> 5.8150061
A7: Foreign direct investment, net inflows (% of GDP) | B7: BX.KLT.DINV.WD.GD.ZS | C7: Cote d'Ivoire | D7: CIV | E7: 0.047488 | F7: -0.03081 | G7: -0.02328 | H7: 0.108996 | I7: -0.10852 | J7: 1.452181 | K7: 1.388232 | L7: 1.543117 | M7: 1.374419 | N7: 1.173391 | O7: 1.026062 | P7: 0.822954 | Q7: 0.909737 | R7: 0.953204 | S7: 0.899529 | T7: 1.079142 | U7: 1.193758 | V7: 1.856735 | W7: 1.059987 | X7: 1.40583 | Y7: 1.131112 | Z7: 1.912827 | AB7: =AVERAGE(E7:Z7) -> 0.96254959
A8: Foreign direct investment, net inflows (% of GDP) | B8: BX.KLT.DINV.WD.GD.ZS | C8: Egypt, Arab Rep. | D8: EGY | E8: 1.236997 | F8: 0.527385 | G8: 0.759753 | H8: 0.295684 | I8: 1.590836 | J8: 5.999509 | K8: 9.348567 | L8: 8.876336 | M8: 5.831413 | N8: 3.548351 | O8: 2.916017 | P8: -0.20454 | Q8: 1.002341 | R8: 1.453434 | S8: 1.50925 | T8: 2.102581 | U8: 2.438563 | V8: 2.983016 | W8: 3.100401 | X8: 2.827329 | Y8: 1.524629 | Z8: 1.206179 | AB8: =AVERAGE(E8:Z8) -> 2.7670014
A9: Foreign direct investment, net inflows (% of GDP) | B9: BX.KLT.DINV.WD.GD.ZS | C9: Ghana | D9: GHA | E9: 3.329419 | F9: 1.680567 | G9: 0.955694 | H9: 1.791641 | I9: 1.568105 | J9: 1.34924 | K9: 3.04529 | L9: 5.571189 | M9: 9.466439 | N9: 9.108087 | O9: 7.849485 | P9: 8.25588 | Q9: 7.982516 | R9: 5.136521 | S9: 6.139441 | T9: 6.461401 | U9: 6.205533 | V9: 5.388528 | W9: 4.441431 | X9: 5.677417 | Y9: 2.678041 | Z9: 3.185923 | AB9: =AVERAGE(E9:Z9) -> 4.8758085
A10: Foreign direct investment, net inflows (% of GDP) | B10: BX.KLT.DINV.WD.GD.ZS | C10: Haiti | D10: HTI | E10: 0.194465 | F10: 0.069489 | G10: 0.091849 | H10: 0.272085 | I10: 0.096922 | J10: 0.369836 | K10: 2.102441 | L10: 0.80727 | M10: 0.285633 | N10: 0.478313 | O10: 1.50093 | P10: 0.914769 | Q10: 1.137945 | R10: 1.08652 | S10: 0.6536 | T10: 0.711668 | U10: 0.745596 | V10: 2.483609 | W10: 0.640093 | X10: 0.499464 | Y10: 0.172316 | Z10: 0.245715 | AB10: =AVERAGE(E10:Z10) -> 0.70729673
A11: Foreign direct investment, net inflows (% of GDP) | B11: BX.KLT.DINV.WD.GD.ZS | C11: Honduras | D11: HND | E11: 4.869843 | F11: 4.049407 | G11: 3.656217 | H11: 4.740556 | I11: 6.676064 | J11: 6.160283 | K11: 6.572873 | L11: 7.822233 | M11: 8.650204 | N11: 3.389872 | O11: 3.834606 | P11: 5.886814 | Q11: 5.83611 | R11: 5.778621 | S11: 8.628997 | T11: 6.275943 | U11: 5.28157 | V11: 4.10592 | W11: 5.993861 | X11: 3.838464 | Y11: 1.010682 | Z11: 2.843613 | AB11: =AVERAGE(E11:Z11) -> 5.268307
A12: Foreign direct investment, net inflows (% of GDP) | B12: BX.KLT.DINV.WD.GD.ZS | C12: India | D12: IND | E12: 0.765212 | F12: 1.05638 | G12: 1.011569 | H12: 0.605888 | I12: 0.765597 | J12: 0.886098 | K12: 2.130168 | L12: 2.073394 | M12: 3.620523 | N12: 2.65159 | O12: 1.635034 | P12: 2.002063 | Q12: 1.312935 | R12: 1.516276 | S12: 1.69566 | T12: 2.092115 | U12: 1.937364 | V12: 1.507316 | W12: 1.558215 | X12: 1.784826 | Y12: 2.406203 | Z12: 1.412171 | AB12: =AVERAGE(E12:Z12) -> 1.6557544
A13: Foreign direct investment, net inflows (% of GDP) | B13: BX.KLT.DINV.WD.GD.ZS | C13: Jordan | D13: JOR | E13: 10.79401 | F13: 3.048505 | G13: 2.486017 | H13: 5.364727 | I13: 8.209223 | J13: 15.76365 | K13: 23.53729 | L13: 15.32483 | M13: 12.47531 | N13: 9.834179 | O13: 6.222476 | P13: 5.033359 | Q13: 4.894807 | R13: 5.649772 | S13: 5.912049 | T13: 4.147202 | U13: 3.892851 | V13: 4.878141 | W13: 2.201777 | X13: 1.639706 | Y13: 1.73976 | Z13: 1.343161 | AB13: =AVERAGE(E13:Z13) -> 7.0178546
... A28: Foreign direct investment, net inflows (% of GDP) | B28: BX.KLT.DINV.WD.GD.ZS | C28: Zambia | D28: ZMB | E28: 3.379962 | F28: 3.541387 | G28: 7.114941 | H28: 7.078931 | I28: 5.851689 | J28: 4.284032 | K28: 4.827129 | L28: 9.418112 | M28: 5.240508 | N28: 4.53278 | O28: 8.533196 | P28: 4.725162 | Q28: 6.789381 | R28: 7.489325 | S28: 5.555428 | T28: 7.447417 | U28: 3.16252 | V28: 4.280501 | W28: 1.552319 | X28: 2.350919 | Y28: 1.351906 | Z28: 1.784078 | AB28: =AVERAGE(E28:Z28) -> 5.0132556
A32: Data from database: World Development Indicators
A33: Last Updated: 01/28/2025
A34: Code | B34: License Type | C34: Indicator Name | D34: Long definition | E34: Source | F34: Topic | G34: Periodicity | H34: Aggregation method | I34: Statistical concept and methodology | J34: Development relevance | K34: Limitations and exceptions | L34: General comments | M34: License URL
A35: BX.KLT.DINV.WD.GD.ZS | B35: CC BY-4.0 | C35: Foreign direct investment, net inflows (% of GDP) | D35: Foreign direct investment are the net inflows of investment to acquire a lasting management interest (10 percent or more of voting stock) in an enterprise operating in an economy other than that of the investor. It is the sum of equity capital, reinvestment of earnings, other long-term capital, and short-term capital as shown in the balance of payments. This series shows net inflows (new investment inflows less disinvestment) in the reporting economy from foreign investors, and is divided by GDP. | E35: International Monetary Fund, International Financial Statistics and Balance of Payments databases, World Bank, International Debt Statistics, and World Bank and OECD GDP estimates. | F35: Economic Policy & Debt: Balance of payments: Capital & financial account | G35: Annual | H35: Weighted average | I35: Data on equity flows are based on balance of payments data reported by the International Monetary Fund (IMF). Foreign direct investment (FDI) data are supplemented by the World Bank staff estimates using data from the United Nations Conference on Trade and Development (UNCTAD) and official national sources. The internationally accepted definition of FDI (from the sixth edition of the IMF's Balance of Payments Manual [2009]), includes the following components: equity investment, including investment associated with equity that gives rise to control or influence; investment in indirectly influenced or controlled enterprises; investment in fellow enterprises; debt (except selected debt); and reverse investment. The Framework for Direct Investment Relationships provides criteria for determining whether cross-border ownership results in a direct investment relationship, based on control and influence. Distinguished from other kinds of international investment, FDI is made to establish a lasting interest in or effective management control over an enterprise in another country. A lasting interest in an investment enterprise typically involves establishing warehouses, manufacturing facilities, and other permanent or long-term organizations abroad. Direct investments may take the form of greenfield investment, where the investor starts a new venture in a foreign country by constructing new operational facilities; joint venture, where the investor enters into a partnership agreement with a company abroad to establish a new enterprise; or merger and acquisition, where the investor acquires an existing enterprise abroad. The IMF suggests that investments should account for at least 10 percent of voting stock to be counted as FDI. In practice many countries set a higher threshold. Many countries fail to report reinvested earnings, and the definition of long-term loans differs among countries. BoP refers to Balance of Payments. | J35: Private financial flows - equity and debt - account for the bulk of development finance. Equity flows comprise foreign direct investment (FDI) and portfolio equity. Debt flows are financing raised through bond issuance, bank lending, and supplier credits. | K35: FDI data do not give a complete picture of international investment in an economy. Balance of payments data on FDI do not include capital raised locally, an important source of investment financing in some developing countries. In addition, FDI data omit nonequity cross-border transactions such as intra-unit flows of goods and services. The volume of global private financial flows reported by the World Bank generally differs from that reported by other sources because of differences in sources, classification of economies, and method used to adjust and disaggregate reported information. In addition, particularly for debt financing, differences may also reflect how some installments of the transactions and certain offshore issuances are treated. Data on equity flows are shown for all countries for which data are available. | L35: Note: Data starting from 2005 are based on the sixth edition of the IMF's Balance of Payments Manual (BPM6). | M35: https://datacatalog.worldbank.org/public-licenses#cc-by

Sheet APPENDIX 
A1: Descriptive Statistics
A2: Notation | B2: Definition | C2: Mean | D2: Median | E2: Maximun | F2: Minimum | G2: Std. Dev. | H2: Skewness | I2: Kurtosis | J2: Sources
A3: ren | B3: Renewable energy consumption as a percentage of total energy consumption | C3: =AVERAGE(REN!B2:W28) -> 49.099832 | D3: =MEDIAN(REN!B2:W28) -> 51.15 | E3: =MAX(REN!B2:W28) -> 93.6 | F3: =MIN(REN!B2:W28) -> 1.7 | G3: =_xlfn.STDEV.S(REN!B2:W28) -> 26.387077 | H3: =SKEW(REN!B2:W28) -> -0.23246822 | I3: =KURT(REN!B2:W28) -> -1.0652707 | J3: World Bank
A4: fd | B4: Financial Development Indicator obtained from the IMF financial statistics database | C4: =AVERAGE(FD!E2:Z28) -> 0.2102862 | D4: =MEDIAN(FD!E2:Z28) -> 0.18 | E4: =MAX(FD!E2:Z28) -> 0.58 | F4: =MIN(FD!E2:Z28) -> 0.03 | G4: =_xlfn.STDEV.S(FD!E2:Z28) -> 0.11248122 | H4: =SKEW(FD!E2:Z28) -> 0.85976765 | I4: =KURT(FD!E2:Z28) -> 0.091017722 | J4: IMF
A5: inst | B5: Index of Institutional quality | C5: =AVERAGE(INST!B2:W28) -> 0.50755892 | D5: =MEDIAN(INST!B2:W28) -> 0.51 | E5: =MAX(INST!B2:W28) -> 0.74 | F5: =MIN(INST!B2:W28) -> 0.23 | G5: =_xlfn.STDEV.S(INST!B2:W28) -> 0.095548125 | H5: =SKEW(INST!B2:W28) -> -0.44581072 | I5: =KURT(INST!B2:W28) -> 0.013276188 | J5: ICRG PRS
A6: lrgdppc | B6: Real GDP per capita(USD$ 2015) | C6: =AVERAGE(RGDPPC!E2:Z28) -> 6817520.4 | D6: =MEDIAN(RGDPPC!E2:Z28) -> 3622432.4 | E6: =MAX(RGDPPC!E2:Z28) -> 80201757 | F6: =MIN(RGDPPC!E2:Z28) -> 89156.265 | G6: =_xlfn.STDEV.S(RGDPPC!E2:Z28) -> 11138787 | H6: =SKEW(RGDPPC!E2:Z28) -> 4.2590329 | I6: =KURT(RGDPPC!E2:Z28) -> 20.60983 | J6: World Bank
A7: fdi | B7: Foreign Direct Investment inflows as a percentage of GDP. | C7: =AVERAGE(FDI!E2:Z28) -> 2.9933859 | D7: =MEDIAN(FDI!E2:Z28) -> 1.9922095 | E7: =MAX(FDI!E2:Z28) -> 34.41826 | F7: =MIN(FDI!E2:Z28) -> -17.2921 | G7: =_xlfn.STDEV.S(FDI!E2:Z28) -> 3.9100855 | H7: =SKEW(FDI!E2:Z28) -> 1.9286175 | I7: =KURT(FDI!E2:Z28) -> 12.221939 | J7: World Bank
A8: lpop | B8: Total population size of country | C8: =AVERAGE(POP!E2:Z28) -> 89935238 | D8: =MEDIAN(POP!E2:Z28) -> 21736500 | E8: =MAX(POP!E2:Z28) -> 1410000000 | F8: =MIN(POP!E2:Z28) -> 3151345 | G8: =_xlfn.STDEV.S(POP!E2:Z28) -> 2.3425568e+08 | H8: =SKEW(POP!E2:Z28) -> 4.5890285 | I8: =KURT(POP!E2:Z28) -> 20.472907 | J8: World Bank
A9: fd*inst | B9: Interaction term between financial development and institutional quality | C9: =AVERAGE(FDxINST!E2:Z28) -> 0.11267626 | D9: =MEDIAN(FDxINST!E2:Z28) -> 0.0936 | E9: =MAX(FDxINST!E2:Z28) -> 0.3828 | F9: =MIN(FDxINST!E2:Z28) -> 0.0129 | G9: =_xlfn.STDEV.S(FDxINST!E2:Z28) -> 0.07526406 | H9: =SKEW(FDxINST!E2:Z28) -> 1.2458183 | I9: =KURT(FDxINST!E2:Z28) -> 1.3081692 | J9: World Bank
B12: Correlation Matrix | C12: ren | D12: fd | E12: inst | F12: rgdppc | G12: fdi | H12: pop
B13: ren | C13: 1
B14: fd | C14: -0.69228 | D14: 1
B15: inst | C15: -0.55463 | D15: 0.618414 | E15: 1
B16: rgdppc | C16: -0.55541 | D16: 0.344573 | E16: 0.214412 | F16: 1
B17: fdi | C17: -0.31259 | D17: 0.1518 | E17: 0.308414 | F17: 0.491474 | G17: 1
B18: pop | C18: -0.07196 | D18: 0.501693 | E18: 0.269713 | F18: -0.13671 | G18: -0.21591 | H18: 1
